[
  {
    "id": 21000001,
    "name": "裂开的豆荚",
    "desc": "可惜播下后长不出东西。",
    "funcDesc": "交易补给。成功带出后自动出售以换取回报。",
    "quality": 1,
    "icon": 1000001,
    "type": 1,
    "dropPrice": 1,
    "dropWeight": 100,
    "subType": 0,
    "price": 70,
    "cost": 10,
    "takeOut": 1,
    "disappear": 0,
    "maxStack": 10,
    "directUse": 0,
    "useEffect": "",
    "useDesc": "",
    "bagSkillIds": "",
    "diceList": "",
    "refrain": "",
    "additionRule": ""
  },
  {
    "id": 21000002,
    "name": "叶子",
    "desc": "带着淡淡的泥土味和一半腐败的叶身。",
    "funcDesc": "交易补给。成功带出后自动出售以换取回报。",
    "quality": 1,
    "icon": 1000002,
    "type": 1,
    "dropPrice": 1,
    "dropWeight": 100,
    "subType": 0,
    "price": 70,
    "cost": 10,
    "takeOut": 1,
    "disappear": 0,
    "maxStack": 10,
    "directUse": 0,
    "useEffect": "",
    "useDesc": "",
    "bagSkillIds": "",
    "diceList": "",
    "refrain": "",
    "additionRule": ""
  },
  {
    "id": 21000003,
    "name": "蜗牛壳",
    "desc": "小心爬上枝头，这就是下场。",
    "funcDesc": "交易补给。成功带出后自动出售以换取回报。",
    "quality": 1,
    "icon": 1000003,
    "type": 1,
    "dropPrice": 1,
    "dropWeight": 100,
    "subType": 0,
    "price": 75,
    "cost": 10,
    "takeOut": 1,
    "disappear": 0,
    "maxStack": 10,
    "directUse": 0,
    "useEffect": "",
    "useDesc": "",
    "bagSkillIds": "",
    "diceList": "",
    "refrain": "",
    "additionRule": ""
  },
  {
    "id": 21000004,
    "name": "昆虫翅膀",
    "desc": "仪器显示它依然在进行震动？",
    "funcDesc": "交易补给。成功带出后自动出售以换取回报。",
    "quality": 1,
    "icon": 1000004,
    "type": 1,
    "dropPrice": 1,
    "dropWeight": 100,
    "subType": 0,
    "price": 80,
    "cost": 8,
    "takeOut": 1,
    "disappear": 0,
    "maxStack": 10,
    "directUse": 0,
    "useEffect": "",
    "useDesc": "",
    "bagSkillIds": "",
    "diceList": "",
    "refrain": "",
    "additionRule": ""
  },
  {
    "id": 21000005,
    "name": "蛹茧",
    "desc": "隐隐约约感受到生命的跳动。",
    "funcDesc": "交易补给。成功带出后自动出售以换取回报。",
    "quality": 2,
    "icon": 1000005,
    "type": 1,
    "dropPrice": 1,
    "dropWeight": 100,
    "subType": 0,
    "price": 95,
    "cost": 8,
    "takeOut": 1,
    "disappear": 0,
    "maxStack": 10,
    "directUse": 0,
    "useEffect": "",
    "useDesc": "",
    "bagSkillIds": "",
    "diceList": "",
    "refrain": "",
    "additionRule": ""
  },
  {
    "id": 21000006,
    "name": "干草丝",
    "desc": "可以点燃取暖，铺下当床，叼在嘴里打发时间。",
    "funcDesc": "交易补给。成功带出后自动出售以换取回报。",
    "quality": 1,
    "icon": 1000006,
    "type": 1,
    "dropPrice": 1,
    "dropWeight": 100,
    "subType": 0,
    "price": 75,
    "cost": 10,
    "takeOut": 1,
    "disappear": 0,
    "maxStack": 10,
    "directUse": 0,
    "useEffect": "",
    "useDesc": "",
    "bagSkillIds": "",
    "diceList": "",
    "refrain": "",
    "additionRule": ""
  },
  {
    "id": 21000007,
    "name": "金属骨头",
    "desc": "史前义肢技术，大概。",
    "funcDesc": "交易补给。成功带出后自动出售以换取回报。",
    "quality": 1,
    "icon": 1000007,
    "type": 1,
    "dropPrice": 1,
    "dropWeight": 100,
    "subType": 0,
    "price": 70,
    "cost": 10,
    "takeOut": 1,
    "disappear": 0,
    "maxStack": 10,
    "directUse": 0,
    "useEffect": "",
    "useDesc": "",
    "bagSkillIds": "",
    "diceList": "",
    "refrain": "",
    "additionRule": ""
  },
  {
    "id": 21000008,
    "name": "石手链",
    "desc": "石头也禁不住时间的啃食。",
    "funcDesc": "交易补给。成功带出后自动出售以换取回报。",
    "quality": 2,
    "icon": 1000008,
    "type": 1,
    "dropPrice": 1,
    "dropWeight": 100,
    "subType": 0,
    "price": 115,
    "cost": 10,
    "takeOut": 1,
    "disappear": 0,
    "maxStack": 10,
    "directUse": 0,
    "useEffect": "",
    "useDesc": "",
    "bagSkillIds": "",
    "diceList": "",
    "refrain": "",
    "additionRule": ""
  },
  {
    "id": 21000009,
    "name": "颜料石头",
    "desc": "你别说，还挺可爱的。",
    "funcDesc": "交易补给。成功带出后自动出售以换取回报。",
    "quality": 1,
    "icon": 1000009,
    "type": 1,
    "dropPrice": 1,
    "dropWeight": 100,
    "subType": 0,
    "price": 75,
    "cost": 12,
    "takeOut": 1,
    "disappear": 0,
    "maxStack": 10,
    "directUse": 0,
    "useEffect": "",
    "useDesc": "",
    "bagSkillIds": "",
    "diceList": "",
    "refrain": "",
    "additionRule": ""
  },
  {
    "id": 21000010,
    "name": "树枝鸟窝",
    "desc": "鸟蛋已经变成鸟儿又变成骸骨了。",
    "funcDesc": "交易补给。成功带出后自动出售以换取回报。",
    "quality": 2,
    "icon": 1000010,
    "type": 1,
    "dropPrice": 1,
    "dropWeight": 100,
    "subType": 0,
    "price": 100,
    "cost": 10,
    "takeOut": 1,
    "disappear": 0,
    "maxStack": 10,
    "directUse": 0,
    "useEffect": "",
    "useDesc": "",
    "bagSkillIds": "",
    "diceList": "",
    "refrain": "",
    "additionRule": ""
  },
  {
    "id": 21000011,
    "name": "吃剩的骨头",
    "desc": "原来是一只振翅的鱼。",
    "funcDesc": "交易补给。成功带出后自动出售以换取回报。",
    "quality": 2,
    "icon": 1000011,
    "type": 1,
    "dropPrice": 1,
    "dropWeight": 100,
    "subType": 0,
    "price": 90,
    "cost": 10,
    "takeOut": 1,
    "disappear": 0,
    "maxStack": 10,
    "directUse": 0,
    "useEffect": "",
    "useDesc": "",
    "bagSkillIds": "",
    "diceList": "",
    "refrain": "",
    "additionRule": ""
  },
  {
    "id": 21000012,
    "name": "贝加尔湖泥",
    "desc": "黑色的湖泥。",
    "funcDesc": "交易补给。成功带出后自动出售以换取回报。",
    "quality": 1,
    "icon": 1000012,
    "type": 1,
    "dropPrice": 1,
    "dropWeight": 100,
    "subType": 0,
    "price": 75,
    "cost": 10,
    "takeOut": 1,
    "disappear": 0,
    "maxStack": 10,
    "directUse": 0,
    "useEffect": "",
    "useDesc": "",
    "bagSkillIds": "",
    "diceList": "",
    "refrain": "",
    "additionRule": ""
  },
  {
    "id": 21000013,
    "name": "奔奔石头",
    "desc": "原始的石头，一点都不潮流。",
    "funcDesc": "交易补给。成功带出后自动出售以换取回报。",
    "quality": 1,
    "icon": 1000013,
    "type": 1,
    "dropPrice": 1,
    "dropWeight": 100,
    "subType": 0,
    "price": 75,
    "cost": 10,
    "takeOut": 1,
    "disappear": 0,
    "maxStack": 10,
    "directUse": 0,
    "useEffect": "",
    "useDesc": "",
    "bagSkillIds": "",
    "diceList": "",
    "refrain": "",
    "additionRule": ""
  },
  {
    "id": 21000014,
    "name": "粗壮树枝",
    "desc": "里面的水分阻止了它变成火把。",
    "funcDesc": "交易补给。成功带出后自动出售以换取回报。",
    "quality": 1,
    "icon": 1000014,
    "type": 1,
    "dropPrice": 1,
    "dropWeight": 100,
    "subType": 0,
    "price": 75,
    "cost": 10,
    "takeOut": 1,
    "disappear": 0,
    "maxStack": 10,
    "directUse": 0,
    "useEffect": "",
    "useDesc": "",
    "bagSkillIds": "",
    "diceList": "",
    "refrain": "",
    "additionRule": ""
  },
  {
    "id": 21000015,
    "name": "断铅笔",
    "desc": "断了！第四根了！",
    "funcDesc": "交易补给。成功带出后自动出售以换取回报。",
    "quality": 2,
    "icon": 1000015,
    "type": 1,
    "dropPrice": 1,
    "dropWeight": 100,
    "subType": 0,
    "price": 110,
    "cost": 10,
    "takeOut": 1,
    "disappear": 0,
    "maxStack": 10,
    "directUse": 0,
    "useEffect": "",
    "useDesc": "",
    "bagSkillIds": "",
    "diceList": "",
    "refrain": "",
    "additionRule": ""
  },
  {
    "id": 21000016,
    "name": "飞溅骨矢",
    "desc": "一般是最初级的弹药。",
    "funcDesc": "交易补给。成功带出后自动出售以换取回报。",
    "quality": 2,
    "icon": 1000016,
    "type": 1,
    "dropPrice": 1,
    "dropWeight": 100,
    "subType": 0,
    "price": 100,
    "cost": 10,
    "takeOut": 1,
    "disappear": 0,
    "maxStack": 10,
    "directUse": 0,
    "useEffect": "",
    "useDesc": "",
    "bagSkillIds": "",
    "diceList": "",
    "refrain": "",
    "additionRule": ""
  },
  {
    "id": 21000017,
    "name": "高级红药水",
    "desc": "你说这棵草能帮我们对抗未知？",
    "funcDesc": "交易补给。成功带出后自动出售以换取回报。",
    "quality": 3,
    "icon": 1000017,
    "type": 1,
    "dropPrice": 1,
    "dropWeight": 100,
    "subType": 0,
    "price": 145,
    "cost": 10,
    "takeOut": 1,
    "disappear": 0,
    "maxStack": 10,
    "directUse": 0,
    "useEffect": "",
    "useDesc": "",
    "bagSkillIds": "",
    "diceList": "",
    "refrain": "",
    "additionRule": ""
  },
  {
    "id": 21000018,
    "name": "高级黄药水",
    "desc": "看着不错，这个能吃吗？",
    "funcDesc": "交易补给。成功带出后自动出售以换取回报。",
    "quality": 3,
    "icon": 1000018,
    "type": 1,
    "dropPrice": 1,
    "dropWeight": 100,
    "subType": 0,
    "price": 150,
    "cost": 10,
    "takeOut": 1,
    "disappear": 0,
    "maxStack": 10,
    "directUse": 0,
    "useEffect": "",
    "useDesc": "",
    "bagSkillIds": "",
    "diceList": "",
    "refrain": "",
    "additionRule": ""
  },
  {
    "id": 21000019,
    "name": "高级灰药水",
    "desc": "如灰尘般死气沉沉。",
    "funcDesc": "交易补给。成功带出后自动出售以换取回报。",
    "quality": 3,
    "icon": 1000019,
    "type": 1,
    "dropPrice": 1,
    "dropWeight": 100,
    "subType": 0,
    "price": 155,
    "cost": 10,
    "takeOut": 1,
    "disappear": 0,
    "maxStack": 10,
    "directUse": 0,
    "useEffect": "",
    "useDesc": "",
    "bagSkillIds": "",
    "diceList": "",
    "refrain": "",
    "additionRule": ""
  },
  {
    "id": 21000020,
    "name": "高级蓝药水",
    "desc": "如大海般汹涌。",
    "funcDesc": "交易补给。成功带出后自动出售以换取回报。",
    "quality": 3,
    "icon": 1000020,
    "type": 1,
    "dropPrice": 1,
    "dropWeight": 100,
    "subType": 0,
    "price": 150,
    "cost": 10,
    "takeOut": 1,
    "disappear": 0,
    "maxStack": 10,
    "directUse": 0,
    "useEffect": "",
    "useDesc": "",
    "bagSkillIds": "",
    "diceList": "",
    "refrain": "",
    "additionRule": ""
  },
  {
    "id": 21000021,
    "name": "高级绿药水",
    "desc": "听起来真的很苦，跟我的命一样。",
    "funcDesc": "交易补给。成功带出后自动出售以换取回报。",
    "quality": 3,
    "icon": 1000021,
    "type": 1,
    "dropPrice": 1,
    "dropWeight": 100,
    "subType": 0,
    "price": 150,
    "cost": 10,
    "takeOut": 1,
    "disappear": 0,
    "maxStack": 10,
    "directUse": 0,
    "useEffect": "",
    "useDesc": "",
    "bagSkillIds": "",
    "diceList": "",
    "refrain": "",
    "additionRule": ""
  },
  {
    "id": 21000022,
    "name": "高级紫药水",
    "desc": "它在诱惑我喝下。",
    "funcDesc": "交易补给。成功带出后自动出售以换取回报。",
    "quality": 3,
    "icon": 1000022,
    "type": 1,
    "dropPrice": 1,
    "dropWeight": 100,
    "subType": 0,
    "price": 150,
    "cost": 10,
    "takeOut": 1,
    "disappear": 0,
    "maxStack": 10,
    "directUse": 0,
    "useEffect": "",
    "useDesc": "",
    "bagSkillIds": "",
    "diceList": "",
    "refrain": "",
    "additionRule": ""
  },
  {
    "id": 21000023,
    "name": "合成工具",
    "desc": "可以自己搓一个合成台。",
    "funcDesc": "交易补给。成功带出后自动出售以换取回报。",
    "quality": 2,
    "icon": 1000023,
    "type": 1,
    "dropPrice": 1,
    "dropWeight": 100,
    "subType": 0,
    "price": 100,
    "cost": 10,
    "takeOut": 1,
    "disappear": 0,
    "maxStack": 10,
    "directUse": 0,
    "useEffect": "",
    "useDesc": "",
    "bagSkillIds": "",
    "diceList": "",
    "refrain": "",
    "additionRule": ""
  },
  {
    "id": 21000024,
    "name": "河的讯息",
    "desc": "来自去年的消息。",
    "funcDesc": "交易补给。成功带出后自动出售以换取回报。",
    "quality": 2,
    "icon": 1000024,
    "type": 1,
    "dropPrice": 1,
    "dropWeight": 100,
    "subType": 0,
    "price": 100,
    "cost": 10,
    "takeOut": 1,
    "disappear": 0,
    "maxStack": 10,
    "directUse": 0,
    "useEffect": "",
    "useDesc": "",
    "bagSkillIds": "",
    "diceList": "",
    "refrain": "",
    "additionRule": ""
  },
  {
    "id": 21000025,
    "name": "黑曜石砖",
    "desc": "本来可以更加锋利的。",
    "funcDesc": "交易补给。成功带出后自动出售以换取回报。",
    "quality": 2,
    "icon": 1000025,
    "type": 1,
    "dropPrice": 1,
    "dropWeight": 100,
    "subType": 0,
    "price": 100,
    "cost": 10,
    "takeOut": 1,
    "disappear": 0,
    "maxStack": 10,
    "directUse": 0,
    "useEffect": "",
    "useDesc": "",
    "bagSkillIds": "",
    "diceList": "",
    "refrain": "",
    "additionRule": ""
  },
  {
    "id": 21000026,
    "name": "高级黄药水",
    "desc": "白色的，甜甜的，快些吃下。",
    "funcDesc": "交易补给。成功带出后自动出售以换取回报。",
    "quality": 3,
    "icon": 1000026,
    "type": 1,
    "dropPrice": 1,
    "dropWeight": 100,
    "subType": 0,
    "price": 150,
    "cost": 10,
    "takeOut": 1,
    "disappear": 0,
    "maxStack": 10,
    "directUse": 0,
    "useEffect": "",
    "useDesc": "",
    "bagSkillIds": "",
    "diceList": "",
    "refrain": "",
    "additionRule": ""
  },
  {
    "id": 21000027,
    "name": "灰药水",
    "desc": "看着像骨灰拌水。",
    "funcDesc": "交易补给。成功带出后自动出售以换取回报。",
    "quality": 3,
    "icon": 1000027,
    "type": 1,
    "dropPrice": 1,
    "dropWeight": 100,
    "subType": 0,
    "price": 150,
    "cost": 10,
    "takeOut": 1,
    "disappear": 0,
    "maxStack": 10,
    "directUse": 0,
    "useEffect": "",
    "useDesc": "",
    "bagSkillIds": "",
    "diceList": "",
    "refrain": "",
    "additionRule": ""
  },
  {
    "id": 21000028,
    "name": "昏眠棒槌",
    "desc": "让你的仇人获得婴儿般的睡眠。",
    "funcDesc": "交易补给。成功带出后自动出售以换取回报。",
    "quality": 2,
    "icon": 1000028,
    "type": 1,
    "dropPrice": 1,
    "dropWeight": 100,
    "subType": 0,
    "price": 100,
    "cost": 10,
    "takeOut": 1,
    "disappear": 0,
    "maxStack": 10,
    "directUse": 0,
    "useEffect": "",
    "useDesc": "",
    "bagSkillIds": "",
    "diceList": "",
    "refrain": "",
    "additionRule": ""
  },
  {
    "id": 21000029,
    "name": "蓝药水",
    "desc": "来自一片灰暗的沙滩。",
    "funcDesc": "交易补给。成功带出后自动出售以换取回报。",
    "quality": 3,
    "icon": 1000029,
    "type": 1,
    "dropPrice": 1,
    "dropWeight": 100,
    "subType": 0,
    "price": 150,
    "cost": 10,
    "takeOut": 1,
    "disappear": 0,
    "maxStack": 10,
    "directUse": 0,
    "useEffect": "",
    "useDesc": "",
    "bagSkillIds": "",
    "diceList": "",
    "refrain": "",
    "additionRule": ""
  },
  {
    "id": 21000030,
    "name": "绿药水",
    "desc": "瓶装草原。",
    "funcDesc": "交易补给。成功带出后自动出售以换取回报。",
    "quality": 3,
    "icon": 1000030,
    "type": 1,
    "dropPrice": 1,
    "dropWeight": 100,
    "subType": 0,
    "price": 150,
    "cost": 10,
    "takeOut": 1,
    "disappear": 0,
    "maxStack": 10,
    "directUse": 0,
    "useEffect": "",
    "useDesc": "",
    "bagSkillIds": "",
    "diceList": "",
    "refrain": "",
    "additionRule": ""
  },
  {
    "id": 21000031,
    "name": "思考的芦苇",
    "desc": "会思考吗？芦苇秆为什么是空心的呢？",
    "funcDesc": "交易补给。成功带出后自动出售以换取回报。",
    "quality": 2,
    "icon": 1000031,
    "type": 1,
    "dropPrice": 1,
    "dropWeight": 100,
    "subType": 0,
    "price": 100,
    "cost": 10,
    "takeOut": 1,
    "disappear": 0,
    "maxStack": 10,
    "directUse": 0,
    "useEffect": "",
    "useDesc": "",
    "bagSkillIds": "",
    "diceList": "",
    "refrain": "",
    "additionRule": ""
  },
  {
    "id": 21000032,
    "name": "忒休斯碎片",
    "desc": "折戟沉沙，一文不值。",
    "funcDesc": "交易补给。成功带出后自动出售以换取回报。",
    "quality": 2,
    "icon": 1000032,
    "type": 1,
    "dropPrice": 1,
    "dropWeight": 100,
    "subType": 0,
    "price": 110,
    "cost": 10,
    "takeOut": 1,
    "disappear": 0,
    "maxStack": 10,
    "directUse": 0,
    "useEffect": "",
    "useDesc": "",
    "bagSkillIds": "",
    "diceList": "",
    "refrain": "",
    "additionRule": ""
  },
  {
    "id": 21000033,
    "name": "手指饰物",
    "desc": "这间屋里最值钱的东西。",
    "funcDesc": "交易补给。成功带出后自动出售以换取回报。",
    "quality": 4,
    "icon": 1000033,
    "type": 1,
    "dropPrice": 1,
    "dropWeight": 100,
    "subType": 0,
    "price": 250,
    "cost": 8,
    "takeOut": 1,
    "disappear": 0,
    "maxStack": 10,
    "directUse": 0,
    "useEffect": "",
    "useDesc": "",
    "bagSkillIds": "",
    "diceList": "",
    "refrain": "",
    "additionRule": ""
  },
  {
    "id": 21000034,
    "name": "龙草",
    "desc": "龙吃完很开心。",
    "funcDesc": "交易补给。成功带出后自动出售以换取回报。",
    "quality": 4,
    "icon": 1000034,
    "type": 1,
    "dropPrice": 1,
    "dropWeight": 100,
    "subType": 0,
    "price": 250,
    "cost": 10,
    "takeOut": 1,
    "disappear": 0,
    "maxStack": 10,
    "directUse": 0,
    "useEffect": "",
    "useDesc": "",
    "bagSkillIds": "",
    "diceList": "",
    "refrain": "",
    "additionRule": ""
  },
  {
    "id": 21000035,
    "name": "幼熊爪",
    "desc": "恶毒的蜂蜜紧紧地黏住了它。",
    "funcDesc": "交易补给。成功带出后自动出售以换取回报。",
    "quality": 4,
    "icon": 1000035,
    "type": 1,
    "dropPrice": 1,
    "dropWeight": 100,
    "subType": 0,
    "price": 250,
    "cost": 10,
    "takeOut": 1,
    "disappear": 0,
    "maxStack": 10,
    "directUse": 0,
    "useEffect": "",
    "useDesc": "",
    "bagSkillIds": "",
    "diceList": "",
    "refrain": "",
    "additionRule": ""
  },
  {
    "id": 21000036,
    "name": "胆腺腐化",
    "desc": "恶臭不堪。",
    "funcDesc": "交易补给。成功带出后自动出售以换取回报。",
    "quality": 4,
    "icon": 1000036,
    "type": 1,
    "dropPrice": 1,
    "dropWeight": 100,
    "subType": 0,
    "price": 250,
    "cost": 10,
    "takeOut": 1,
    "disappear": 0,
    "maxStack": 10,
    "directUse": 0,
    "useEffect": "",
    "useDesc": "",
    "bagSkillIds": "",
    "diceList": "",
    "refrain": "",
    "additionRule": ""
  },
  {
    "id": 21000037,
    "name": "风干鱼骨",
    "desc": "脆脆的……什么，不能食用吗？",
    "funcDesc": "交易补给。成功带出后自动出售以换取回报。",
    "quality": 4,
    "icon": 1000037,
    "type": 1,
    "dropPrice": 1,
    "dropWeight": 100,
    "subType": 0,
    "price": 250,
    "cost": 10,
    "takeOut": 1,
    "disappear": 0,
    "maxStack": 10,
    "directUse": 0,
    "useEffect": "",
    "useDesc": "",
    "bagSkillIds": "",
    "diceList": "",
    "refrain": "",
    "additionRule": ""
  },
  {
    "id": 21000038,
    "name": "碎裂的后槽牙",
    "desc": "它被人还回来了，不行，得再给我一颗！",
    "funcDesc": "交易补给。成功带出后自动出售以换取回报。",
    "quality": 4,
    "icon": 1000038,
    "type": 1,
    "dropPrice": 1,
    "dropWeight": 100,
    "subType": 0,
    "price": 250,
    "cost": 10,
    "takeOut": 1,
    "disappear": 0,
    "maxStack": 10,
    "directUse": 0,
    "useEffect": "",
    "useDesc": "",
    "bagSkillIds": "",
    "diceList": "",
    "refrain": "",
    "additionRule": ""
  },
  {
    "id": 21000039,
    "name": "“北”的间隙",
    "desc": "指哪儿都算北。",
    "funcDesc": "交易补给。成功带出后自动出售以换取回报。",
    "quality": 4,
    "icon": 1000039,
    "type": 1,
    "dropPrice": 1,
    "dropWeight": 100,
    "subType": 0,
    "price": 275,
    "cost": 10,
    "takeOut": 1,
    "disappear": 0,
    "maxStack": 10,
    "directUse": 0,
    "useEffect": "",
    "useDesc": "",
    "bagSkillIds": "",
    "diceList": "",
    "refrain": "",
    "additionRule": ""
  },
  {
    "id": 21000040,
    "name": "胆小蒺藜",
    "desc": "这还算得上是胆子大的。",
    "funcDesc": "交易补给。成功带出后自动出售以换取回报。",
    "quality": 4,
    "icon": 1000040,
    "type": 1,
    "dropPrice": 1,
    "dropWeight": 100,
    "subType": 0,
    "price": 250,
    "cost": 10,
    "takeOut": 1,
    "disappear": 0,
    "maxStack": 10,
    "directUse": 0,
    "useEffect": "",
    "useDesc": "",
    "bagSkillIds": "",
    "diceList": "",
    "refrain": "",
    "additionRule": ""
  },
  {
    "id": 21000041,
    "name": "胃袋",
    "desc": "充满了胃液。",
    "funcDesc": "交易补给。成功带出后自动出售以换取回报。",
    "quality": 4,
    "icon": 1000041,
    "type": 1,
    "dropPrice": 1,
    "dropWeight": 100,
    "subType": 0,
    "price": 250,
    "cost": 10,
    "takeOut": 1,
    "disappear": 0,
    "maxStack": 10,
    "directUse": 0,
    "useEffect": "",
    "useDesc": "",
    "bagSkillIds": "",
    "diceList": "",
    "refrain": "",
    "additionRule": ""
  },
  {
    "id": 21000042,
    "name": "1号病原体",
    "desc": "一滴就能杀死一只浣熊。",
    "funcDesc": "交易补给。成功带出后自动出售以换取回报。",
    "quality": 4,
    "icon": 1000042,
    "type": 1,
    "dropPrice": 1,
    "dropWeight": 100,
    "subType": 0,
    "price": 250,
    "cost": 5,
    "takeOut": 1,
    "disappear": 0,
    "maxStack": 10,
    "directUse": 0,
    "useEffect": "",
    "useDesc": "",
    "bagSkillIds": "",
    "diceList": "",
    "refrain": "",
    "additionRule": ""
  },
  {
    "id": 21000043,
    "name": "破伤风菜刀",
    "desc": "潜伏期一般为10天。",
    "funcDesc": "交易补给。成功带出后自动出售以换取回报。",
    "quality": 4,
    "icon": 1000043,
    "type": 1,
    "dropPrice": 1,
    "dropWeight": 100,
    "subType": 0,
    "price": 250,
    "cost": 15,
    "takeOut": 1,
    "disappear": 0,
    "maxStack": 10,
    "directUse": 0,
    "useEffect": "",
    "useDesc": "",
    "bagSkillIds": "",
    "diceList": "",
    "refrain": "",
    "additionRule": ""
  },
  {
    "id": 21000044,
    "name": "呕吐熏香",
    "desc": "好闻到吐。",
    "funcDesc": "交易补给。成功带出后自动出售以换取回报。",
    "quality": 4,
    "icon": 1000044,
    "type": 1,
    "dropPrice": 1,
    "dropWeight": 100,
    "subType": 0,
    "price": 250,
    "cost": 10,
    "takeOut": 1,
    "disappear": 0,
    "maxStack": 10,
    "directUse": 0,
    "useEffect": "",
    "useDesc": "",
    "bagSkillIds": "",
    "diceList": "",
    "refrain": "",
    "additionRule": ""
  },
  {
    "id": 21000045,
    "name": "咒用扭结",
    "desc": "群星，沙海，淹没了所有一切应当之物。",
    "funcDesc": "交易补给。成功带出后自动出售以换取回报。",
    "quality": 4,
    "icon": 1000045,
    "type": 1,
    "dropPrice": 1,
    "dropWeight": 100,
    "subType": 0,
    "price": 225,
    "cost": 7,
    "takeOut": 1,
    "disappear": 0,
    "maxStack": 10,
    "directUse": 0,
    "useEffect": "",
    "useDesc": "",
    "bagSkillIds": "",
    "diceList": "",
    "refrain": "",
    "additionRule": ""
  },
  {
    "id": 21000046,
    "name": "植物果实",
    "desc": "自然规则理应如此。",
    "funcDesc": "交易补给。成功带出后自动出售以换取回报。",
    "quality": 4,
    "icon": 1000046,
    "type": 1,
    "dropPrice": 1,
    "dropWeight": 100,
    "subType": 0,
    "price": 250,
    "cost": 10,
    "takeOut": 1,
    "disappear": 0,
    "maxStack": 10,
    "directUse": 0,
    "useEffect": "",
    "useDesc": "",
    "bagSkillIds": "",
    "diceList": "",
    "refrain": "",
    "additionRule": ""
  },
  {
    "id": 21000047,
    "name": "蛙皮提袋",
    "desc": "简单快捷，还可以挂在腰间。",
    "funcDesc": "交易补给。成功带出后自动出售以换取回报。",
    "quality": 4,
    "icon": 1000047,
    "type": 1,
    "dropPrice": 1,
    "dropWeight": 100,
    "subType": 0,
    "price": 250,
    "cost": 10,
    "takeOut": 1,
    "disappear": 0,
    "maxStack": 10,
    "directUse": 0,
    "useEffect": "",
    "useDesc": "",
    "bagSkillIds": "",
    "diceList": "",
    "refrain": "",
    "additionRule": ""
  },
  {
    "id": 21000048,
    "name": "灼热钢铁",
    "desc": "高楼的脊梁。",
    "funcDesc": "交易补给。成功带出后自动出售以换取回报。",
    "quality": 4,
    "icon": 1000048,
    "type": 1,
    "dropPrice": 1,
    "dropWeight": 100,
    "subType": 0,
    "price": 250,
    "cost": 12,
    "takeOut": 1,
    "disappear": 0,
    "maxStack": 10,
    "directUse": 0,
    "useEffect": "",
    "useDesc": "",
    "bagSkillIds": "",
    "diceList": "",
    "refrain": "",
    "additionRule": ""
  },
  {
    "id": 21000049,
    "name": "焚烧的垃圾",
    "desc": "永不熄灭的火焰。",
    "funcDesc": "交易补给。成功带出后自动出售以换取回报。",
    "quality": 4,
    "icon": 1000049,
    "type": 1,
    "dropPrice": 1,
    "dropWeight": 100,
    "subType": 0,
    "price": 225,
    "cost": 10,
    "takeOut": 1,
    "disappear": 0,
    "maxStack": 10,
    "directUse": 0,
    "useEffect": "",
    "useDesc": "",
    "bagSkillIds": "",
    "diceList": "",
    "refrain": "",
    "additionRule": ""
  },
  {
    "id": 21000050,
    "name": "侦查望远镜",
    "desc": "越看越远的奇怪望远镜。",
    "funcDesc": "交易补给。成功带出后自动出售以换取回报。",
    "quality": 4,
    "icon": 1000050,
    "type": 1,
    "dropPrice": 1,
    "dropWeight": 100,
    "subType": 0,
    "price": 250,
    "cost": 10,
    "takeOut": 1,
    "disappear": 0,
    "maxStack": 10,
    "directUse": 0,
    "useEffect": "",
    "useDesc": "",
    "bagSkillIds": "",
    "diceList": "",
    "refrain": "",
    "additionRule": ""
  },
  {
    "id": 21000051,
    "name": "神秘藏宝图",
    "desc": "向北15米，再向南15米。",
    "funcDesc": "交易补给。成功带出后自动出售以换取回报。",
    "quality": 4,
    "icon": 1000051,
    "type": 1,
    "dropPrice": 1,
    "dropWeight": 100,
    "subType": 0,
    "price": 275,
    "cost": 10,
    "takeOut": 1,
    "disappear": 0,
    "maxStack": 10,
    "directUse": 0,
    "useEffect": "",
    "useDesc": "",
    "bagSkillIds": "",
    "diceList": "",
    "refrain": "",
    "additionRule": ""
  },
  {
    "id": 21000052,
    "name": "树枝上的羽毛",
    "desc": "随风飞翔，一如往日。",
    "funcDesc": "交易补给。成功带出后自动出售以换取回报。",
    "quality": 4,
    "icon": 1000052,
    "type": 1,
    "dropPrice": 1,
    "dropWeight": 100,
    "subType": 0,
    "price": 250,
    "cost": 5,
    "takeOut": 1,
    "disappear": 0,
    "maxStack": 10,
    "directUse": 0,
    "useEffect": "",
    "useDesc": "",
    "bagSkillIds": "",
    "diceList": "",
    "refrain": "",
    "additionRule": ""
  },
  {
    "id": 21000053,
    "name": "木化兽齿",
    "desc": "它发芽了。",
    "funcDesc": "交易补给。成功带出后自动出售以换取回报。",
    "quality": 4,
    "icon": 1000053,
    "type": 1,
    "dropPrice": 1,
    "dropWeight": 100,
    "subType": 0,
    "price": 250,
    "cost": 10,
    "takeOut": 1,
    "disappear": 0,
    "maxStack": 10,
    "directUse": 0,
    "useEffect": "",
    "useDesc": "",
    "bagSkillIds": "",
    "diceList": "",
    "refrain": "",
    "additionRule": ""
  },
  {
    "id": 21000054,
    "name": "亚平宁黑石",
    "desc": "热情如火，却如黑石。",
    "funcDesc": "交易补给。成功带出后自动出售以换取回报。",
    "quality": 4,
    "icon": 1000054,
    "type": 1,
    "dropPrice": 1,
    "dropWeight": 100,
    "subType": 0,
    "price": 250,
    "cost": 12,
    "takeOut": 1,
    "disappear": 0,
    "maxStack": 10,
    "directUse": 0,
    "useEffect": "",
    "useDesc": "",
    "bagSkillIds": "",
    "diceList": "",
    "refrain": "",
    "additionRule": ""
  },
  {
    "id": 21000055,
    "name": "金色隐虫标本",
    "desc": "听说价值连城，但是无人问津。",
    "funcDesc": "交易补给。成功带出后自动出售以换取回报。",
    "quality": 4,
    "icon": 1000055,
    "type": 1,
    "dropPrice": 1,
    "dropWeight": 100,
    "subType": 0,
    "price": 250,
    "cost": 8,
    "takeOut": 1,
    "disappear": 0,
    "maxStack": 10,
    "directUse": 0,
    "useEffect": "",
    "useDesc": "",
    "bagSkillIds": "",
    "diceList": "",
    "refrain": "",
    "additionRule": ""
  },
  {
    "id": 21000056,
    "name": "罗勒蜜罐",
    "desc": "传说它曾依靠它的甜蜜和粘性折断过一只熊掌。",
    "funcDesc": "交易补给。成功带出后自动出售以换取回报。",
    "quality": 4,
    "icon": 1000056,
    "type": 1,
    "dropPrice": 1,
    "dropWeight": 100,
    "subType": 0,
    "price": 250,
    "cost": 10,
    "takeOut": 1,
    "disappear": 0,
    "maxStack": 10,
    "directUse": 0,
    "useEffect": "",
    "useDesc": "",
    "bagSkillIds": "",
    "diceList": "",
    "refrain": "",
    "additionRule": ""
  },
  {
    "id": 21000057,
    "name": "黑尘",
    "desc": "遮天盖日的黑灰蒙住了所有的光。",
    "funcDesc": "交易补给。成功带出后自动出售以换取回报。",
    "quality": 4,
    "icon": 1000057,
    "type": 1,
    "dropPrice": 1,
    "dropWeight": 100,
    "subType": 0,
    "price": 250,
    "cost": 3,
    "takeOut": 1,
    "disappear": 0,
    "maxStack": 10,
    "directUse": 0,
    "useEffect": "",
    "useDesc": "",
    "bagSkillIds": "",
    "diceList": "",
    "refrain": "",
    "additionRule": ""
  },
  {
    "id": 21000058,
    "name": "球状蜂巢",
    "desc": "嗡嗡嗡——",
    "funcDesc": "交易补给。成功带出后自动出售以换取回报。",
    "quality": 4,
    "icon": 1000058,
    "type": 1,
    "dropPrice": 1,
    "dropWeight": 100,
    "subType": 0,
    "price": 250,
    "cost": 10,
    "takeOut": 1,
    "disappear": 0,
    "maxStack": 10,
    "directUse": 0,
    "useEffect": "",
    "useDesc": "",
    "bagSkillIds": "",
    "diceList": "",
    "refrain": "",
    "additionRule": ""
  },
  {
    "id": 21000059,
    "name": "伞蜥皱领",
    "desc": "我们得到它的时候就是这样的！",
    "funcDesc": "交易补给。成功带出后自动出售以换取回报。",
    "quality": 4,
    "icon": 1000059,
    "type": 1,
    "dropPrice": 1,
    "dropWeight": 100,
    "subType": 0,
    "price": 250,
    "cost": 10,
    "takeOut": 1,
    "disappear": 0,
    "maxStack": 10,
    "directUse": 0,
    "useEffect": "",
    "useDesc": "",
    "bagSkillIds": "",
    "diceList": "",
    "refrain": "",
    "additionRule": ""
  },
  {
    "id": 21000060,
    "name": "拖把与水桶",
    "desc": "破烂得像野外求生临时制作的。",
    "funcDesc": "交易补给。成功带出后自动出售以换取回报。",
    "quality": 4,
    "icon": 1000060,
    "type": 1,
    "dropPrice": 1,
    "dropWeight": 100,
    "subType": 0,
    "price": 250,
    "cost": 12,
    "takeOut": 1,
    "disappear": 0,
    "maxStack": 10,
    "directUse": 0,
    "useEffect": "",
    "useDesc": "",
    "bagSkillIds": "",
    "diceList": "",
    "refrain": "",
    "additionRule": ""
  },
  {
    "id": 21000061,
    "name": "系铃的手鼓",
    "desc": "敲下去发出的第一声是什么样的？",
    "funcDesc": "交易补给。成功带出后自动出售以换取回报。",
    "quality": 4,
    "icon": 1000061,
    "type": 1,
    "dropPrice": 1,
    "dropWeight": 100,
    "subType": 0,
    "price": 250,
    "cost": 10,
    "takeOut": 1,
    "disappear": 0,
    "maxStack": 10,
    "directUse": 0,
    "useEffect": "",
    "useDesc": "",
    "bagSkillIds": "",
    "diceList": "",
    "refrain": "",
    "additionRule": ""
  },
  {
    "id": 21000062,
    "name": "登山杖",
    "desc": "历经数位主人，现在轮到你了。",
    "funcDesc": "交易补给。成功带出后自动出售以换取回报。",
    "quality": 4,
    "icon": 1000062,
    "type": 1,
    "dropPrice": 1,
    "dropWeight": 100,
    "subType": 0,
    "price": 250,
    "cost": 10,
    "takeOut": 1,
    "disappear": 0,
    "maxStack": 10,
    "directUse": 0,
    "useEffect": "",
    "useDesc": "",
    "bagSkillIds": "",
    "diceList": "",
    "refrain": "",
    "additionRule": ""
  },
  {
    "id": 21000063,
    "name": "球状毒腺",
    "desc": "刻有奇怪的符号，看起来是十六进制？",
    "funcDesc": "交易补给。成功带出后自动出售以换取回报。",
    "quality": 5,
    "icon": 1000063,
    "type": 1,
    "dropPrice": 1,
    "dropWeight": 100,
    "subType": 0,
    "price": 500,
    "cost": 10,
    "takeOut": 1,
    "disappear": 0,
    "maxStack": 10,
    "directUse": 0,
    "useEffect": "",
    "useDesc": "",
    "bagSkillIds": "",
    "diceList": "",
    "refrain": "",
    "additionRule": ""
  },
  {
    "id": 21000064,
    "name": "不灭旌旗",
    "desc": "喝下之后无所不能。",
    "funcDesc": "交易补给。成功带出后自动出售以换取回报。",
    "quality": 5,
    "icon": 1000064,
    "type": 1,
    "dropPrice": 1,
    "dropWeight": 100,
    "subType": 0,
    "price": 500,
    "cost": 10,
    "takeOut": 1,
    "disappear": 0,
    "maxStack": 10,
    "directUse": 0,
    "useEffect": "",
    "useDesc": "",
    "bagSkillIds": "",
    "diceList": "",
    "refrain": "",
    "additionRule": ""
  },
  {
    "id": 21000065,
    "name": "山羊头骨",
    "desc": "黑山羊，藏在羊群里的黑山羊。",
    "funcDesc": "交易补给。成功带出后自动出售以换取回报。",
    "quality": 5,
    "icon": 1000065,
    "type": 1,
    "dropPrice": 1,
    "dropWeight": 100,
    "subType": 0,
    "price": 500,
    "cost": 12,
    "takeOut": 1,
    "disappear": 0,
    "maxStack": 10,
    "directUse": 0,
    "useEffect": "",
    "useDesc": "",
    "bagSkillIds": "",
    "diceList": "",
    "refrain": "",
    "additionRule": ""
  },
  {
    "id": 21000066,
    "name": "生的褶皱",
    "desc": "它的一生都在试图抚平自己。",
    "funcDesc": "交易补给。成功带出后自动出售以换取回报。",
    "quality": 5,
    "icon": 1000066,
    "type": 1,
    "dropPrice": 1,
    "dropWeight": 100,
    "subType": 0,
    "price": 480,
    "cost": 10,
    "takeOut": 1,
    "disappear": 0,
    "maxStack": 10,
    "directUse": 0,
    "useEffect": "",
    "useDesc": "",
    "bagSkillIds": "",
    "diceList": "",
    "refrain": "",
    "additionRule": ""
  },
  {
    "id": 21000067,
    "name": "死亡之花",
    "desc": "听说会开在人的胸口？",
    "funcDesc": "交易补给。成功带出后自动出售以换取回报。",
    "quality": 5,
    "icon": 1000067,
    "type": 1,
    "dropPrice": 1,
    "dropWeight": 100,
    "subType": 0,
    "price": 550,
    "cost": 8,
    "takeOut": 1,
    "disappear": 0,
    "maxStack": 10,
    "directUse": 0,
    "useEffect": "",
    "useDesc": "",
    "bagSkillIds": "",
    "diceList": "",
    "refrain": "",
    "additionRule": ""
  },
  {
    "id": 21000068,
    "name": "未知恐惧",
    "desc": "恐惧本身就是一种未知。",
    "funcDesc": "交易补给。成功带出后自动出售以换取回报。",
    "quality": 5,
    "icon": 1000068,
    "type": 1,
    "dropPrice": 1,
    "dropWeight": 100,
    "subType": 0,
    "price": 500,
    "cost": 10,
    "takeOut": 1,
    "disappear": 0,
    "maxStack": 10,
    "directUse": 0,
    "useEffect": "",
    "useDesc": "",
    "bagSkillIds": "",
    "diceList": "",
    "refrain": "",
    "additionRule": ""
  },
  {
    "id": 21000069,
    "name": "奉献之卵",
    "desc": "在这儿的祭坛上虔诚地供奉它。",
    "funcDesc": "交易补给。成功带出后自动出售以换取回报。",
    "quality": 5,
    "icon": 1000069,
    "type": 1,
    "dropPrice": 1,
    "dropWeight": 100,
    "subType": 0,
    "price": 520,
    "cost": 5,
    "takeOut": 1,
    "disappear": 0,
    "maxStack": 10,
    "directUse": 0,
    "useEffect": "",
    "useDesc": "",
    "bagSkillIds": "",
    "diceList": "",
    "refrain": "",
    "additionRule": ""
  },
  {
    "id": 21000070,
    "name": "实用真菌学",
    "desc": "确实实用，食用后致死率100%。",
    "funcDesc": "交易补给。成功带出后自动出售以换取回报。",
    "quality": 5,
    "icon": 1000070,
    "type": 1,
    "dropPrice": 1,
    "dropWeight": 100,
    "subType": 0,
    "price": 500,
    "cost": 10,
    "takeOut": 1,
    "disappear": 0,
    "maxStack": 10,
    "directUse": 0,
    "useEffect": "",
    "useDesc": "",
    "bagSkillIds": "",
    "diceList": "",
    "refrain": "",
    "additionRule": ""
  },
  {
    "id": 21000071,
    "name": "雄鹿的斗争",
    "desc": "败者和胜者最后都只能留下这个。",
    "funcDesc": "交易补给。成功带出后自动出售以换取回报。",
    "quality": 5,
    "icon": 1000071,
    "type": 1,
    "dropPrice": 1,
    "dropWeight": 100,
    "subType": 0,
    "price": 500,
    "cost": 10,
    "takeOut": 1,
    "disappear": 0,
    "maxStack": 10,
    "directUse": 0,
    "useEffect": "",
    "useDesc": "",
    "bagSkillIds": "",
    "diceList": "",
    "refrain": "",
    "additionRule": ""
  },
  {
    "id": 21000072,
    "name": "雅拉瓜壁虎琥珀",
    "desc": "连尾巴都没来得及断。",
    "funcDesc": "交易补给。成功带出后自动出售以换取回报。",
    "quality": 5,
    "icon": 1000072,
    "type": 1,
    "dropPrice": 1,
    "dropWeight": 100,
    "subType": 0,
    "price": 500,
    "cost": 10,
    "takeOut": 1,
    "disappear": 0,
    "maxStack": 10,
    "directUse": 0,
    "useEffect": "",
    "useDesc": "",
    "bagSkillIds": "",
    "diceList": "",
    "refrain": "",
    "additionRule": ""
  },
  {
    "id": 21000073,
    "name": "诅咒硬币",
    "desc": "见血方得激情与真理。",
    "funcDesc": "交易补给。成功带出后自动出售以换取回报。",
    "quality": 5,
    "icon": 1000073,
    "type": 1,
    "dropPrice": 1,
    "dropWeight": 100,
    "subType": 0,
    "price": 480,
    "cost": 8,
    "takeOut": 1,
    "disappear": 0,
    "maxStack": 10,
    "directUse": 0,
    "useEffect": "",
    "useDesc": "",
    "bagSkillIds": "",
    "diceList": "",
    "refrain": "",
    "additionRule": ""
  },
  {
    "id": 21000074,
    "name": "古老刻痕",
    "desc": "剑从此处下，一会儿记得捞。",
    "funcDesc": "交易补给。成功带出后自动出售以换取回报。",
    "quality": 5,
    "icon": 1000074,
    "type": 1,
    "dropPrice": 1,
    "dropWeight": 100,
    "subType": 0,
    "price": 500,
    "cost": 10,
    "takeOut": 1,
    "disappear": 0,
    "maxStack": 10,
    "directUse": 0,
    "useEffect": "",
    "useDesc": "",
    "bagSkillIds": "",
    "diceList": "",
    "refrain": "",
    "additionRule": ""
  },
  {
    "id": 21000075,
    "name": "贮灵壶",
    "desc": "灵魂的居所。",
    "funcDesc": "交易补给。成功带出后自动出售以换取回报。",
    "quality": 5,
    "icon": 1000075,
    "type": 1,
    "dropPrice": 1,
    "dropWeight": 100,
    "subType": 0,
    "price": 500,
    "cost": 10,
    "takeOut": 1,
    "disappear": 0,
    "maxStack": 10,
    "directUse": 0,
    "useEffect": "",
    "useDesc": "",
    "bagSkillIds": "",
    "diceList": "",
    "refrain": "",
    "additionRule": ""
  },
  {
    "id": 21000076,
    "name": "山楂木瘿",
    "desc": "不安地扭曲着，然后更不安了。",
    "funcDesc": "交易补给。成功带出后自动出售以换取回报。",
    "quality": 5,
    "icon": 1000076,
    "type": 1,
    "dropPrice": 1,
    "dropWeight": 100,
    "subType": 0,
    "price": 500,
    "cost": 10,
    "takeOut": 1,
    "disappear": 0,
    "maxStack": 10,
    "directUse": 0,
    "useEffect": "",
    "useDesc": "",
    "bagSkillIds": "",
    "diceList": "",
    "refrain": "",
    "additionRule": ""
  },
  {
    "id": 21000077,
    "name": "黑羊之角",
    "desc": "白山羊，白山羊在羊群里。",
    "funcDesc": "交易补给。成功带出后自动出售以换取回报。",
    "quality": 5,
    "icon": 1000077,
    "type": 1,
    "dropPrice": 1,
    "dropWeight": 100,
    "subType": 0,
    "price": 500,
    "cost": 10,
    "takeOut": 1,
    "disappear": 0,
    "maxStack": 10,
    "directUse": 0,
    "useEffect": "",
    "useDesc": "",
    "bagSkillIds": "",
    "diceList": "",
    "refrain": "",
    "additionRule": ""
  },
  {
    "id": 21000078,
    "name": "契约匕首",
    "desc": "契约的效力取决于匕首本身。",
    "funcDesc": "交易补给。成功带出后自动出售以换取回报。",
    "quality": 5,
    "icon": 1000078,
    "type": 1,
    "dropPrice": 1,
    "dropWeight": 100,
    "subType": 0,
    "price": 500,
    "cost": 10,
    "takeOut": 1,
    "disappear": 0,
    "maxStack": 10,
    "directUse": 0,
    "useEffect": "",
    "useDesc": "",
    "bagSkillIds": "",
    "diceList": "",
    "refrain": "",
    "additionRule": ""
  },
  {
    "id": 21000079,
    "name": "诅咒铠甲",
    "desc": "一看就被诅咒过。",
    "funcDesc": "交易补给。成功带出后自动出售以换取回报。",
    "quality": 5,
    "icon": 1000079,
    "type": 1,
    "dropPrice": 1,
    "dropWeight": 100,
    "subType": 0,
    "price": 550,
    "cost": 12,
    "takeOut": 1,
    "disappear": 0,
    "maxStack": 10,
    "directUse": 0,
    "useEffect": "",
    "useDesc": "",
    "bagSkillIds": "",
    "diceList": "",
    "refrain": "",
    "additionRule": ""
  },
  {
    "id": 21000080,
    "name": "第一泥板",
    "desc": "它见证了这个没落文明的第一个文字。",
    "funcDesc": "交易补给。成功带出后自动出售以换取回报。",
    "quality": 5,
    "icon": 1000080,
    "type": 1,
    "dropPrice": 1,
    "dropWeight": 100,
    "subType": 0,
    "price": 500,
    "cost": 12,
    "takeOut": 1,
    "disappear": 0,
    "maxStack": 10,
    "directUse": 0,
    "useEffect": "",
    "useDesc": "",
    "bagSkillIds": "",
    "diceList": "",
    "refrain": "",
    "additionRule": ""
  },
  {
    "id": 21000081,
    "name": "硬质星光",
    "desc": "追寻天空中红色的星星。",
    "funcDesc": "交易补给。成功带出后自动出售以换取回报。",
    "quality": 5,
    "icon": 1000081,
    "type": 1,
    "dropPrice": 1,
    "dropWeight": 100,
    "subType": 0,
    "price": 500,
    "cost": 10,
    "takeOut": 1,
    "disappear": 0,
    "maxStack": 10,
    "directUse": 0,
    "useEffect": "",
    "useDesc": "",
    "bagSkillIds": "",
    "diceList": "",
    "refrain": "",
    "additionRule": ""
  },
  {
    "id": 21000082,
    "name": "酣睡捕网",
    "desc": "冒失的飞蝇总是不小心。",
    "funcDesc": "交易补给。成功带出后自动出售以换取回报。",
    "quality": 5,
    "icon": 1000082,
    "type": 1,
    "dropPrice": 1,
    "dropWeight": 100,
    "subType": 0,
    "price": 500,
    "cost": 10,
    "takeOut": 1,
    "disappear": 0,
    "maxStack": 10,
    "directUse": 0,
    "useEffect": "",
    "useDesc": "",
    "bagSkillIds": "",
    "diceList": "",
    "refrain": "",
    "additionRule": ""
  },
  {
    "id": 21000083,
    "name": "号角",
    "desc": "呜——",
    "funcDesc": "交易补给。成功带出后自动出售以换取回报。",
    "quality": 5,
    "icon": 1000083,
    "type": 1,
    "dropPrice": 1,
    "dropWeight": 100,
    "subType": 0,
    "price": 500,
    "cost": 10,
    "takeOut": 1,
    "disappear": 0,
    "maxStack": 10,
    "directUse": 0,
    "useEffect": "",
    "useDesc": "",
    "bagSkillIds": "",
    "diceList": "",
    "refrain": "",
    "additionRule": ""
  },
  {
    "id": 21000084,
    "name": "硫磺球",
    "desc": "应急发电用。",
    "funcDesc": "交易补给。成功带出后自动出售以换取回报。",
    "quality": 5,
    "icon": 1000084,
    "type": 1,
    "dropPrice": 1,
    "dropWeight": 100,
    "subType": 0,
    "price": 500,
    "cost": 10,
    "takeOut": 1,
    "disappear": 0,
    "maxStack": 10,
    "directUse": 0,
    "useEffect": "",
    "useDesc": "",
    "bagSkillIds": "",
    "diceList": "",
    "refrain": "",
    "additionRule": ""
  },
  {
    "id": 21000085,
    "name": "荆棘皇冠",
    "desc": "皇冠是你的荣誉，也是你的诅咒。",
    "funcDesc": "交易补给。成功带出后自动出售以换取回报。",
    "quality": 5,
    "icon": 1000085,
    "type": 1,
    "dropPrice": 1,
    "dropWeight": 100,
    "subType": 0,
    "price": 520,
    "cost": 10,
    "takeOut": 1,
    "disappear": 0,
    "maxStack": 10,
    "directUse": 0,
    "useEffect": "",
    "useDesc": "",
    "bagSkillIds": "",
    "diceList": "",
    "refrain": "",
    "additionRule": ""
  },
  {
    "id": 21000086,
    "name": "机械手臂",
    "desc": "很可惜，它没有被安装电源。",
    "funcDesc": "交易补给。成功带出后自动出售以换取回报。",
    "quality": 5,
    "icon": 1000086,
    "type": 1,
    "dropPrice": 1,
    "dropWeight": 100,
    "subType": 0,
    "price": 500,
    "cost": 12,
    "takeOut": 1,
    "disappear": 0,
    "maxStack": 10,
    "directUse": 0,
    "useEffect": "",
    "useDesc": "",
    "bagSkillIds": "",
    "diceList": "",
    "refrain": "",
    "additionRule": ""
  },
  {
    "id": 21000087,
    "name": "令人困惑的日晷",
    "desc": "好奇怪啊，真的好奇怪啊。",
    "funcDesc": "非常贵重的交易补给。成功带出后自动出售以换取大量回报。",
    "quality": 6,
    "icon": 1000087,
    "type": 1,
    "dropPrice": 1,
    "dropWeight": 100,
    "subType": 0,
    "price": 1800,
    "cost": 10,
    "takeOut": 1,
    "disappear": 0,
    "maxStack": 1,
    "directUse": 0,
    "useEffect": "",
    "useDesc": "",
    "bagSkillIds": "",
    "diceList": "",
    "refrain": "",
    "additionRule": ""
  },
  {
    "id": 21000088,
    "name": "翡翠戒指",
    "desc": "屋里第三值钱的。",
    "funcDesc": "非常贵重的交易补给。成功带出后自动出售以换取大量回报。",
    "quality": 6,
    "icon": 1000088,
    "type": 1,
    "dropPrice": 1,
    "dropWeight": 100,
    "subType": 0,
    "price": 1999,
    "cost": 10,
    "takeOut": 1,
    "disappear": 0,
    "maxStack": 1,
    "directUse": 0,
    "useEffect": "",
    "useDesc": "",
    "bagSkillIds": "",
    "diceList": "",
    "refrain": "",
    "additionRule": ""
  },
  {
    "id": 21000089,
    "name": "荆棘与蛇蜕",
    "desc": "晶莹剔透，美不胜收。",
    "funcDesc": "非常贵重的交易补给。成功带出后自动出售以换取大量回报。",
    "quality": 6,
    "icon": 1000089,
    "type": 1,
    "dropPrice": 1,
    "dropWeight": 100,
    "subType": 0,
    "price": 1800,
    "cost": 10,
    "takeOut": 1,
    "disappear": 0,
    "maxStack": 1,
    "directUse": 0,
    "useEffect": "",
    "useDesc": "",
    "bagSkillIds": "",
    "diceList": "",
    "refrain": "",
    "additionRule": ""
  },
  {
    "id": 21000090,
    "name": "愚人金",
    "desc": "创意无价，所以蠢人总是发财。",
    "funcDesc": "非常贵重的交易补给。成功带出后自动出售以换取大量回报。",
    "quality": 6,
    "icon": 1000090,
    "type": 1,
    "dropPrice": 1,
    "dropWeight": 100,
    "subType": 0,
    "price": 1800,
    "cost": 15,
    "takeOut": 1,
    "disappear": 0,
    "maxStack": 1,
    "directUse": 0,
    "useEffect": "",
    "useDesc": "",
    "bagSkillIds": "",
    "diceList": "",
    "refrain": "",
    "additionRule": ""
  },
  {
    "id": 21000091,
    "name": "巨型圣甲虫护身符",
    "desc": "它托举太阳。",
    "funcDesc": "非常贵重的交易补给。成功带出后自动出售以换取大量回报。",
    "quality": 6,
    "icon": 1000091,
    "type": 1,
    "dropPrice": 1,
    "dropWeight": 100,
    "subType": 0,
    "price": 1800,
    "cost": 12,
    "takeOut": 1,
    "disappear": 0,
    "maxStack": 1,
    "directUse": 0,
    "useEffect": "",
    "useDesc": "",
    "bagSkillIds": "",
    "diceList": "",
    "refrain": "",
    "additionRule": ""
  },
  {
    "id": 21000092,
    "name": "必要的“知识”",
    "desc": "必要的只有运气。",
    "funcDesc": "非常贵重的交易补给。成功带出后自动出售以换取大量回报。",
    "quality": 6,
    "icon": 1000092,
    "type": 1,
    "dropPrice": 1,
    "dropWeight": 100,
    "subType": 0,
    "price": 1999,
    "cost": 12,
    "takeOut": 1,
    "disappear": 0,
    "maxStack": 1,
    "directUse": 0,
    "useEffect": "",
    "useDesc": "",
    "bagSkillIds": "",
    "diceList": "",
    "refrain": "",
    "additionRule": ""
  },
  {
    "id": 21000094,
    "name": "木质眼睛",
    "desc": "它们一直都在看着你呀，你没发现吗？",
    "funcDesc": "非常贵重的交易补给。成功带出后自动出售以换取大量回报。",
    "quality": 6,
    "icon": 1000094,
    "type": 1,
    "dropPrice": 1,
    "dropWeight": 100,
    "subType": 0,
    "price": 1800,
    "cost": 10,
    "takeOut": 1,
    "disappear": 0,
    "maxStack": 1,
    "directUse": 0,
    "useEffect": "",
    "useDesc": "",
    "bagSkillIds": "",
    "diceList": "",
    "refrain": "",
    "additionRule": ""
  },
  {
    "id": 21000095,
    "name": "断裂龙趾",
    "desc": "巨龙刚死亡，它就被砍下换来了一场盛大的婚礼。",
    "funcDesc": "非常贵重的交易补给。成功带出后自动出售以换取大量回报。",
    "quality": 6,
    "icon": 1000095,
    "type": 1,
    "dropPrice": 1,
    "dropWeight": 100,
    "subType": 0,
    "price": 1800,
    "cost": 10,
    "takeOut": 1,
    "disappear": 0,
    "maxStack": 1,
    "directUse": 0,
    "useEffect": "",
    "useDesc": "",
    "bagSkillIds": "",
    "diceList": "",
    "refrain": "",
    "additionRule": ""
  },
  {
    "id": 21000096,
    "name": "结晶心",
    "desc": "从此忠贞不贰。",
    "funcDesc": "非常贵重的交易补给。成功带出后自动出售以换取大量回报。",
    "quality": 6,
    "icon": 1000096,
    "type": 1,
    "dropPrice": 1,
    "dropWeight": 100,
    "subType": 0,
    "price": 1999,
    "cost": 5,
    "takeOut": 1,
    "disappear": 0,
    "maxStack": 1,
    "directUse": 0,
    "useEffect": "",
    "useDesc": "",
    "bagSkillIds": "",
    "diceList": "",
    "refrain": "",
    "additionRule": ""
  },
  {
    "id": 21000097,
    "name": "光的凝视",
    "desc": "凝视的光。",
    "funcDesc": "非常贵重的交易补给。成功带出后自动出售以换取大量回报。",
    "quality": 6,
    "icon": 1000097,
    "type": 1,
    "dropPrice": 1,
    "dropWeight": 100,
    "subType": 0,
    "price": 1800,
    "cost": 10,
    "takeOut": 1,
    "disappear": 0,
    "maxStack": 1,
    "directUse": 0,
    "useEffect": "",
    "useDesc": "",
    "bagSkillIds": "",
    "diceList": "",
    "refrain": "",
    "additionRule": ""
  },
  {
    "id": 21000098,
    "name": "咒语同频武器",
    "desc": "已经不再象征纯洁。",
    "funcDesc": "非常贵重的交易补给。成功带出后自动出售以换取大量回报。",
    "quality": 6,
    "icon": 1000098,
    "type": 1,
    "dropPrice": 1,
    "dropWeight": 100,
    "subType": 0,
    "price": 1800,
    "cost": 10,
    "takeOut": 1,
    "disappear": 0,
    "maxStack": 1,
    "directUse": 0,
    "useEffect": "",
    "useDesc": "",
    "bagSkillIds": "",
    "diceList": "",
    "refrain": "",
    "additionRule": ""
  },
  {
    "id": 21000099,
    "name": "佩珀尔之光",
    "desc": "反射出的光照亮了黑暗。",
    "funcDesc": "非常贵重的交易补给。成功带出后自动出售以换取大量回报。",
    "quality": 6,
    "icon": 1000099,
    "type": 1,
    "dropPrice": 1,
    "dropWeight": 100,
    "subType": 0,
    "price": 1800,
    "cost": 10,
    "takeOut": 1,
    "disappear": 0,
    "maxStack": 1,
    "directUse": 0,
    "useEffect": "",
    "useDesc": "",
    "bagSkillIds": "",
    "diceList": "",
    "refrain": "",
    "additionRule": ""
  },
  {
    "id": 21000100,
    "name": "狂暴血清",
    "desc": "喝完之后就会彻底不识字了。",
    "funcDesc": "非常贵重的交易补给。成功带出后自动出售以换取大量回报。",
    "quality": 6,
    "icon": 1000100,
    "type": 1,
    "dropPrice": 1,
    "dropWeight": 100,
    "subType": 0,
    "price": 1800,
    "cost": 10,
    "takeOut": 1,
    "disappear": 0,
    "maxStack": 1,
    "directUse": 0,
    "useEffect": "",
    "useDesc": "",
    "bagSkillIds": "",
    "diceList": "",
    "refrain": "",
    "additionRule": ""
  },
  {
    "id": 21000101,
    "name": "宝石饰品",
    "desc": "这是屋里第二值钱的。",
    "funcDesc": "非常贵重的交易补给。成功带出后自动出售以换取大量回报。",
    "quality": 6,
    "icon": 1000101,
    "type": 1,
    "dropPrice": 1,
    "dropWeight": 100,
    "subType": 0,
    "price": 1999,
    "cost": 8,
    "takeOut": 1,
    "disappear": 0,
    "maxStack": 1,
    "directUse": 0,
    "useEffect": "",
    "useDesc": "",
    "bagSkillIds": "",
    "diceList": "",
    "refrain": "",
    "additionRule": ""
  },
  {
    "id": 21000102,
    "name": "庇护之根",
    "desc": "自然会平等地保护所有人。",
    "funcDesc": "非常贵重的交易补给。成功带出后自动出售以换取大量回报。",
    "quality": 6,
    "icon": 1000102,
    "type": 1,
    "dropPrice": 1,
    "dropWeight": 100,
    "subType": 0,
    "price": 1800,
    "cost": 10,
    "takeOut": 1,
    "disappear": 0,
    "maxStack": 1,
    "directUse": 0,
    "useEffect": "",
    "useDesc": "",
    "bagSkillIds": "",
    "diceList": "",
    "refrain": "",
    "additionRule": ""
  },
  {
    "id": 21000103,
    "name": "多动流沙",
    "desc": "给它打点镇静剂我们能不能安全些？",
    "funcDesc": "非常贵重的交易补给。成功带出后自动出售以换取大量回报。",
    "quality": 6,
    "icon": 1000103,
    "type": 1,
    "dropPrice": 1,
    "dropWeight": 100,
    "subType": 0,
    "price": 1800,
    "cost": 8,
    "takeOut": 1,
    "disappear": 0,
    "maxStack": 1,
    "directUse": 0,
    "useEffect": "",
    "useDesc": "",
    "bagSkillIds": "",
    "diceList": "",
    "refrain": "",
    "additionRule": ""
  },
  {
    "id": 21000104,
    "name": "倒置沙漏",
    "desc": "时间不会倒流。",
    "funcDesc": "非常贵重的交易补给。成功带出后自动出售以换取大量回报。",
    "quality": 6,
    "icon": 1000104,
    "type": 1,
    "dropPrice": 1,
    "dropWeight": 100,
    "subType": 0,
    "price": 1999,
    "cost": 8,
    "takeOut": 1,
    "disappear": 0,
    "maxStack": 1,
    "directUse": 0,
    "useEffect": "",
    "useDesc": "",
    "bagSkillIds": "",
    "diceList": "",
    "refrain": "",
    "additionRule": ""
  },
  {
    "id": 22000001,
    "name": "枯萎的树叶",
    "desc": "已经枯萎的黄金树叶，仍保留着微弱的共鸣。",
    "funcDesc": "共鸣触媒，可用于事件共鸣而获得更好奖励。",
    "quality": 2,
    "icon": 2000005,
    "type": 2,
    "dropPrice": 1,
    "dropWeight": 100,
    "subType": 201,
    "price": 0,
    "cost": 0,
    "takeOut": 0,
    "disappear": 0,
    "maxStack": 1,
    "directUse": 0,
    "useEffect": "",
    "useDesc": "",
    "bagSkillIds": "",
    "diceList": "",
    "refrain": "",
    "additionRule": ""
  },
  {
    "id": 22000002,
    "name": "黄金树叶Ⅰ",
    "desc": "状态稳定的黄金树叶，叶脉里仍有清晰光泽。",
    "funcDesc": "共鸣触媒，可用于事件共鸣而获得更好奖励。增加事件对应的花色骰子2个。",
    "quality": 3,
    "icon": 2000022,
    "type": 2,
    "dropPrice": 1,
    "dropWeight": 100,
    "subType": 201,
    "price": 0,
    "cost": 0,
    "takeOut": 0,
    "disappear": 0,
    "maxStack": 1,
    "directUse": 0,
    "useEffect": "",
    "useDesc": "",
    "bagSkillIds": "",
    "diceList": "1370001#1370001",
    "refrain": "",
    "additionRule": ""
  },
  {
    "id": 22000003,
    "name": "黄金树叶Ⅱ",
    "desc": "品质更高的黄金树叶，共鸣比普通版本更强。",
    "funcDesc": "共鸣触媒，可用于事件共鸣而获得更好奖励。增加事件对应的花色骰子4个。",
    "quality": 4,
    "icon": 2000037,
    "type": 2,
    "dropPrice": 1,
    "dropWeight": 100,
    "subType": 201,
    "price": 0,
    "cost": 0,
    "takeOut": 0,
    "disappear": 0,
    "maxStack": 1,
    "directUse": 0,
    "useEffect": "",
    "useDesc": "",
    "bagSkillIds": "",
    "diceList": "1370001#1370001#1370001#1370001",
    "refrain": "",
    "additionRule": ""
  },
  {
    "id": 22000004,
    "name": "黄金树叶Ⅲ",
    "desc": "保存极好的黄金树叶，叶面仍像刚刚从枝头摘下。",
    "funcDesc": "共鸣触媒，可用于事件共鸣而获得更好奖励。增加事件对应的花色骰子6个。",
    "quality": 5,
    "icon": 2000023,
    "type": 2,
    "dropPrice": 1,
    "dropWeight": 100,
    "subType": 201,
    "price": 0,
    "cost": 0,
    "takeOut": 0,
    "disappear": 0,
    "maxStack": 1,
    "directUse": 0,
    "useEffect": "",
    "useDesc": "",
    "bagSkillIds": "",
    "diceList": "1370001#1370001#1370001#1370001#1370001#1370001",
    "refrain": "",
    "additionRule": ""
  },
  {
    "id": 22000005,
    "name": "金黄蜜糖",
    "desc": "一罐黏稠发亮的金黄蜜糖，闻起来甜得发腻。",
    "funcDesc": "行前补给，可用于突发事件。直接使用回复60点耐心，【清晨】下食用效果减半。",
    "quality": 2,
    "icon": 2000024,
    "type": 2,
    "dropPrice": 1,
    "dropWeight": 100,
    "subType": 202,
    "price": 0,
    "cost": 0,
    "takeOut": 0,
    "disappear": 0,
    "maxStack": 1,
    "directUse": 1,
    "useEffect": "refection#60#0#24000014:-30",
    "useDesc": "蜜糖黏得发腻，疲惫被慢慢压下去",
    "bagSkillIds": "",
    "diceList": "1370002#1370002",
    "refrain": "",
    "additionRule": ""
  },
  {
    "id": 22000006,
    "name": "清澈泉水",
    "desc": "干净透亮的泉水，瓶壁还残留着凉意。",
    "funcDesc": "行前补给，可用于突发事件。直接使用回复60耐心，【中午】使用效果翻倍。",
    "quality": 4,
    "icon": 2000025,
    "type": 2,
    "dropPrice": 1,
    "dropWeight": 100,
    "subType": 202,
    "price": 0,
    "cost": 0,
    "takeOut": 0,
    "disappear": 0,
    "maxStack": 1,
    "directUse": 1,
    "useEffect": "refection#80#0#24000015:80",
    "useDesc": "泉水入口，燥热和倦意一起退开",
    "bagSkillIds": "",
    "diceList": "1370002#1370002",
    "refrain": "",
    "additionRule": ""
  },
  {
    "id": 22000007,
    "name": "沸腾烈酒",
    "desc": "气味辛烈的烈酒，液体始终翻着细泡。",
    "funcDesc": "行前补给，可用于突发事件。直接使用回复60耐心，【夜晚】使用效果翻倍。",
    "quality": 4,
    "icon": 2000026,
    "type": 2,
    "dropPrice": 1,
    "dropWeight": 100,
    "subType": 202,
    "price": 0,
    "cost": 0,
    "takeOut": 0,
    "disappear": 0,
    "maxStack": 1,
    "directUse": 1,
    "useEffect": "refection#80#0#24000016:80",
    "useDesc": "烈酒灼过胸口，人一下子顶住了",
    "bagSkillIds": "",
    "diceList": "1370002#1370002#1370002",
    "refrain": "",
    "additionRule": ""
  },
  {
    "id": 22000008,
    "name": "甘蔗糖汁",
    "desc": "颜色浑厚的甘蔗糖汁，底部有明显沉淀。",
    "funcDesc": "行前补给，可用于突发事件。直接使用回复80点耐心。",
    "quality": 3,
    "icon": 2000027,
    "type": 2,
    "dropPrice": 1,
    "dropWeight": 100,
    "subType": 202,
    "price": 0,
    "cost": 0,
    "takeOut": 0,
    "disappear": 0,
    "maxStack": 1,
    "directUse": 1,
    "useEffect": "refection#80#0",
    "useDesc": "糖汁沉进胃里，空乏被填住一截",
    "bagSkillIds": "",
    "diceList": "1370002#1370002#1370002",
    "refrain": "",
    "additionRule": ""
  },
  {
    "id": 22000009,
    "name": "拷苦目糖",
    "desc": "味道发苦的硬糖，表面裹着细薄糖霜。",
    "funcDesc": "行前补给，可用于突发事件。直接使用回复100点耐心，【夜晚】使用效果减半。",
    "quality": 2,
    "icon": 2000028,
    "type": 2,
    "dropPrice": 1,
    "dropWeight": 100,
    "subType": 202,
    "price": 0,
    "cost": 0,
    "takeOut": 0,
    "disappear": 0,
    "maxStack": 1,
    "directUse": 1,
    "useEffect": "refection#60#0#24000016:-30",
    "useDesc": "苦味顶在舌根，眼皮没那么沉了",
    "bagSkillIds": "",
    "diceList": "1370002#1370002#1370002#1370007",
    "refrain": "",
    "additionRule": ""
  },
  {
    "id": 22000010,
    "name": "咸糖块",
    "desc": "带咸味的糖块，外表粗糙，硬度很高。",
    "funcDesc": "行前补给，可用于突发事件。直接使用回复100点耐心，【中午】使用效果减半。",
    "quality": 2,
    "icon": 2000029,
    "type": 2,
    "dropPrice": 1,
    "dropWeight": 100,
    "subType": 202,
    "price": 0,
    "cost": 0,
    "takeOut": 0,
    "disappear": 0,
    "maxStack": 1,
    "directUse": 1,
    "useEffect": "refection#60#0#24000015:-30",
    "useDesc": "咸甜味化开，手脚重新有了劲",
    "bagSkillIds": "",
    "diceList": "1370002#1370002#1370002#1370007",
    "refrain": "",
    "additionRule": ""
  },
  {
    "id": 22000011,
    "name": "抗生素",
    "desc": "一板常规抗生素，包装还算完整。",
    "funcDesc": "医疗保障，可用于突发事件。直接使用随机消除1张珍奇品质状态牌。",
    "quality": 2,
    "icon": 2000030,
    "type": 2,
    "dropPrice": 1,
    "dropWeight": 100,
    "subType": 203,
    "price": 0,
    "cost": 0,
    "takeOut": 0,
    "disappear": 0,
    "maxStack": 1,
    "directUse": 1,
    "useEffect": "randomRemoveItem#4#4#0#1",
    "useDesc": "药片下去，那股不对劲被压住了",
    "bagSkillIds": "",
    "diceList": "1370003#1370003",
    "refrain": "",
    "additionRule": ""
  },
  {
    "id": 22000012,
    "name": "绷带",
    "desc": "一卷处理干净的绷带，边角压得很整齐。",
    "funcDesc": "医疗保障，可用于突发事件。直接使用随机消除1张珍奇品质状态牌。",
    "quality": 2,
    "icon": 2000019,
    "type": 2,
    "dropPrice": 1,
    "dropWeight": 100,
    "subType": 203,
    "price": 0,
    "cost": 0,
    "takeOut": 0,
    "disappear": 0,
    "maxStack": 1,
    "directUse": 1,
    "useEffect": "randomRemoveItem#4#4#0#1",
    "useDesc": "绷带收紧，伤处不再总是牵扯",
    "bagSkillIds": "",
    "diceList": "1370003#1370003",
    "refrain": "",
    "additionRule": ""
  },
  {
    "id": 22000013,
    "name": "强效治疗药",
    "desc": "药效更强的治疗药剂，瓶身有明显医疗标记。",
    "funcDesc": "医疗保障，可用于突发事件。直接使用随机消除1张传闻品质状态牌。",
    "quality": 3,
    "icon": 2000018,
    "type": 2,
    "dropPrice": 1,
    "dropWeight": 100,
    "subType": 203,
    "price": 0,
    "cost": 0,
    "takeOut": 0,
    "disappear": 0,
    "maxStack": 1,
    "directUse": 1,
    "useEffect": "randomRemoveItem#4#5#0#1",
    "useDesc": "药劲散开，不适被清出去一块",
    "bagSkillIds": "",
    "diceList": "1370003#1370003#1370003",
    "refrain": "",
    "additionRule": ""
  },
  {
    "id": 22000014,
    "name": "肾上腺素",
    "desc": "装量饱满的肾上腺素，针剂部分封存完好。",
    "funcDesc": "医疗保障，可用于突发事件。直接使用随机消除1张传闻品质状态牌。",
    "quality": 3,
    "icon": 2000017,
    "type": 2,
    "dropPrice": 1,
    "dropWeight": 100,
    "subType": 203,
    "price": 0,
    "cost": 0,
    "takeOut": 0,
    "disappear": 0,
    "maxStack": 1,
    "directUse": 1,
    "useEffect": "randomRemoveItem#4#5#0#1",
    "useDesc": "针剂推完，意识从边缘被拉回来",
    "bagSkillIds": "",
    "diceList": "1370003#1370003#1370003",
    "refrain": "",
    "additionRule": ""
  },
  {
    "id": 22000015,
    "name": "医疗剂",
    "desc": "便携医疗剂，金属外壳上印着剂量刻度。",
    "funcDesc": "医疗保障，可用于突发事件。直接使用随机消除1张传闻/未知品质状态牌。",
    "quality": 4,
    "icon": 2000020,
    "type": 2,
    "dropPrice": 1,
    "dropWeight": 100,
    "subType": 203,
    "price": 0,
    "cost": 0,
    "takeOut": 0,
    "disappear": 0,
    "maxStack": 1,
    "directUse": 1,
    "useEffect": "randomRemoveItem#4#5,6#0#1",
    "useDesc": "医疗剂压住乱象，身体重新站稳",
    "bagSkillIds": "",
    "diceList": "1370003#1370003#1370003#1370003#1370003",
    "refrain": "",
    "additionRule": ""
  },
  {
    "id": 22000016,
    "name": "医疗包",
    "desc": "塞满药品和器具的医疗包，扣带都还结实。",
    "funcDesc": "医疗保障，可用于突发事件。直接使用随机消除1张传闻/未知品质状态牌。",
    "quality": 4,
    "icon": 2000015,
    "type": 2,
    "dropPrice": 1,
    "dropWeight": 100,
    "subType": 203,
    "price": 0,
    "cost": 0,
    "takeOut": 0,
    "disappear": 0,
    "maxStack": 1,
    "directUse": 1,
    "useEffect": "randomRemoveItem#4#5,6#0#1",
    "useDesc": "医疗包摊开，最棘手的麻烦被收住",
    "bagSkillIds": "",
    "diceList": "1370003#1370003#1370003#1370003#1370003",
    "refrain": "",
    "additionRule": ""
  },
  {
    "id": 22000017,
    "name": "侦查机器人1型",
    "desc": "小型侦查机器人，机身有明显磨损但还能工作。",
    "funcDesc": "勘察道具，可用于突发事件。直接使用获得随机1张珍奇品质对策牌。",
    "quality": 2,
    "icon": 2000031,
    "type": 2,
    "dropPrice": 1,
    "dropWeight": 100,
    "subType": 204,
    "price": 0,
    "cost": 0,
    "takeOut": 0,
    "disappear": 0,
    "maxStack": 1,
    "directUse": 1,
    "useEffect": "randomAddItem#3#4#0#1",
    "useDesc": "机器人回来了，带回一条能用的路",
    "bagSkillIds": "",
    "diceList": "1370005#1370005",
    "refrain": "",
    "additionRule": ""
  },
  {
    "id": 22000018,
    "name": "侦查机器人2型",
    "desc": "升级版侦查机器人，外壳更厚，镜头也更多。",
    "funcDesc": "勘察道具，可用于突发事件。直接使用获得随机1张珍奇品质对策牌。",
    "quality": 2,
    "icon": 2000032,
    "type": 2,
    "dropPrice": 1,
    "dropWeight": 100,
    "subType": 204,
    "price": 0,
    "cost": 0,
    "takeOut": 0,
    "disappear": 0,
    "maxStack": 1,
    "directUse": 1,
    "useEffect": "randomAddItem#3#4#0#1",
    "useDesc": "镜头扫过暗处，新的办法浮了出来",
    "bagSkillIds": "",
    "diceList": "1370005#1370005",
    "refrain": "",
    "additionRule": ""
  },
  {
    "id": 22000019,
    "name": "望远镜",
    "desc": "便携望远镜，镜片边缘还算清晰。",
    "funcDesc": "勘察道具，可用于突发事件。直接使用获得随机1张传闻品质对策牌。",
    "quality": 3,
    "icon": 2000034,
    "type": 2,
    "dropPrice": 1,
    "dropWeight": 100,
    "subType": 204,
    "price": 0,
    "cost": 0,
    "takeOut": 0,
    "disappear": 0,
    "maxStack": 1,
    "directUse": 1,
    "useEffect": "randomAddItem#3#5#0#1",
    "useDesc": "远处轮廓清楚了，选择也跟着多了",
    "bagSkillIds": "",
    "diceList": "1370005#1370005#1370005",
    "refrain": "",
    "additionRule": ""
  },
  {
    "id": 22000020,
    "name": "指南针",
    "desc": "做工扎实的指南针，指针始终在轻微摆动。",
    "funcDesc": "勘察道具，可用于突发事件。直接使用获得随机1张传闻品质对策牌。",
    "quality": 3,
    "icon": 2000038,
    "type": 2,
    "dropPrice": 1,
    "dropWeight": 100,
    "subType": 204,
    "price": 0,
    "cost": 0,
    "takeOut": 0,
    "disappear": 0,
    "maxStack": 1,
    "directUse": 1,
    "useEffect": "randomAddItem#3#5#0#1",
    "useDesc": "指针定住，下一步不再全靠猜",
    "bagSkillIds": "",
    "diceList": "1370005#1370005#1370005",
    "refrain": "",
    "additionRule": ""
  },
  {
    "id": 22000021,
    "name": "撬棍",
    "desc": "有明显撬痕的金属撬棍，适合强行破拆。",
    "funcDesc": "勘察道具，可用于突发事件。直接使用获得1张未知品质对策牌。",
    "quality": 4,
    "icon": 2000021,
    "type": 2,
    "dropPrice": 1,
    "dropWeight": 100,
    "subType": 204,
    "price": 0,
    "cost": 0,
    "takeOut": 0,
    "disappear": 0,
    "maxStack": 1,
    "directUse": 1,
    "useEffect": "randomAddItem#3#6#0#1",
    "useDesc": "撬棍咬进缝里，硬路被撬出入口",
    "bagSkillIds": "",
    "diceList": "1370005#1370005#1370005#1370005#1370005",
    "refrain": "",
    "additionRule": ""
  },
  {
    "id": 22000022,
    "name": "工具箱",
    "desc": "装着常用器具的工具箱，内部格子分得很细。",
    "funcDesc": "勘察道具，可用于突发事件。直接使用获得1张未知品质对策牌。",
    "quality": 4,
    "icon": 2000013,
    "type": 2,
    "dropPrice": 1,
    "dropWeight": 100,
    "subType": 204,
    "price": 0,
    "cost": 0,
    "takeOut": 0,
    "disappear": 0,
    "maxStack": 1,
    "directUse": 1,
    "useEffect": "randomAddItem#3#6#0#1",
    "useDesc": "工具箱打开，棘手处有了下手点",
    "bagSkillIds": "",
    "diceList": "1370005#1370005#1370005#1370005#1370005",
    "refrain": "",
    "additionRule": ""
  },
  {
    "id": 22000023,
    "name": "覆面兜帽",
    "desc": "能遮住大半张脸的兜帽，布料厚实。",
    "funcDesc": "随行装备，可用于突发事件。直接使用消除3张【笨拙】【昏昏欲睡】状态牌。",
    "quality": 2,
    "icon": 2000004,
    "type": 2,
    "dropPrice": 1,
    "dropWeight": 100,
    "subType": 205,
    "price": 0,
    "cost": 0,
    "takeOut": 0,
    "disappear": 0,
    "maxStack": 1,
    "directUse": 1,
    "useEffect": "randomRemoveItem#0#0#24000011,24000007#3",
    "useDesc": "兜帽压住风声，手脚和眼皮都稳了些",
    "bagSkillIds": "",
    "diceList": "1370003#1370003",
    "refrain": "",
    "additionRule": ""
  },
  {
    "id": 22000024,
    "name": "羽毛围巾",
    "desc": "缝着羽毛的围巾，触感轻却很保暖。",
    "funcDesc": "随行装备，可用于突发事件。直接使用消除3张【自动应对】【躁郁症】状态牌。",
    "quality": 2,
    "icon": 2000035,
    "type": 2,
    "dropPrice": 1,
    "dropWeight": 100,
    "subType": 205,
    "price": 0,
    "cost": 0,
    "takeOut": 0,
    "disappear": 0,
    "maxStack": 1,
    "directUse": 1,
    "useEffect": "randomRemoveItem#0#0#24000004,24000005#3",
    "useDesc": "羽毛贴住颈侧，躁动被一点点捂住",
    "bagSkillIds": "",
    "diceList": "1370003#1370003",
    "refrain": "",
    "additionRule": ""
  },
  {
    "id": 22000025,
    "name": "猎手腰带",
    "desc": "结实的猎手腰带，挂扣和口袋都很多。",
    "funcDesc": "随行装备，可用于突发事件。直接使用消除3张【思维混乱】【第三只手】状态牌。",
    "quality": 3,
    "icon": 2000036,
    "type": 2,
    "dropPrice": 1,
    "dropWeight": 100,
    "subType": 205,
    "price": 0,
    "cost": 0,
    "takeOut": 0,
    "disappear": 0,
    "maxStack": 1,
    "directUse": 1,
    "useEffect": "randomRemoveItem#0#0#24000002,24000003#3",
    "useDesc": "腰带扣紧，乱掉的念头和动作都被收回",
    "bagSkillIds": "",
    "diceList": "1370003#1370003#1370003",
    "refrain": "",
    "additionRule": ""
  },
  {
    "id": 22000026,
    "name": "提袋",
    "desc": "容量适中的提袋，边角已经被反复摩擦得发亮。",
    "funcDesc": "随行装备，可用于突发事件。直接使用回复25%的耐心。",
    "quality": 3,
    "icon": 2000003,
    "type": 2,
    "dropPrice": 1,
    "dropWeight": 100,
    "subType": 205,
    "price": 0,
    "cost": 0,
    "takeOut": 0,
    "disappear": 0,
    "maxStack": 1,
    "directUse": 1,
    "useEffect": "refection#0#250",
    "useDesc": "提袋接过重量，肩背终于松了一点",
    "bagSkillIds": "",
    "diceList": "1370003#1370003#1370003",
    "refrain": "",
    "additionRule": ""
  },
  {
    "id": 22000027,
    "name": "高筒靴子",
    "desc": "一双结实的高筒靴，鞋底做过明显加固。",
    "funcDesc": "随行装备，可用于突发事件。直接使用回复50%的耐心。",
    "quality": 4,
    "icon": 2000010,
    "type": 2,
    "dropPrice": 1,
    "dropWeight": 100,
    "subType": 205,
    "price": 0,
    "cost": 0,
    "takeOut": 0,
    "disappear": 0,
    "maxStack": 1,
    "directUse": 1,
    "useEffect": "refection#0#500",
    "useDesc": "靴底抓住地面，剩下的路还能走",
    "bagSkillIds": "",
    "diceList": "1370003#1370003#1370003#1370003#1370003",
    "refrain": "",
    "additionRule": ""
  },
  {
    "id": 23000001,
    "name": "岩系克制对策Ⅳ",
    "desc": "针对岩系弱点的基础对策，适合应对岩系灵感敌人。",
    "funcDesc": "针对【岩】系灵感敌人的对策牌，使用后在战斗中能获得额外伤害。",
    "quality": 4,
    "icon": 3000001,
    "type": 3,
    "dropPrice": 1,
    "dropWeight": 100,
    "subType": 0,
    "price": 0,
    "cost": 0,
    "takeOut": 0,
    "disappear": 0,
    "maxStack": 10,
    "directUse": 0,
    "useEffect": "",
    "useDesc": "",
    "bagSkillIds": "",
    "diceList": "",
    "refrain": "1",
    "additionRule": "2#109370201"
  },
  {
    "id": 23000002,
    "name": "岩系克制对策Ⅴ",
    "desc": "针对岩系弱点的进阶对策，能更稳定地扩大克制效果。",
    "funcDesc": "针对【岩】系灵感敌人的对策牌，使用后在战斗中能获得额外伤害。",
    "quality": 5,
    "icon": 3000001,
    "type": 3,
    "dropPrice": 1,
    "dropWeight": 100,
    "subType": 0,
    "price": 0,
    "cost": 0,
    "takeOut": 0,
    "disappear": 0,
    "maxStack": 10,
    "directUse": 0,
    "useEffect": "",
    "useDesc": "",
    "bagSkillIds": "",
    "diceList": "",
    "refrain": "1",
    "additionRule": "2#109370207"
  },
  {
    "id": 23000006,
    "name": "星系克制对策Ⅳ",
    "desc": "针对星系弱点的基础对策，适合应对星系灵感敌人。",
    "funcDesc": "针对【星】系灵感敌人的对策牌，使用后在战斗中能获得额外伤害。",
    "quality": 4,
    "icon": 3000002,
    "type": 3,
    "dropPrice": 1,
    "dropWeight": 100,
    "subType": 0,
    "price": 0,
    "cost": 0,
    "takeOut": 0,
    "disappear": 0,
    "maxStack": 10,
    "directUse": 0,
    "useEffect": "",
    "useDesc": "",
    "bagSkillIds": "",
    "diceList": "",
    "refrain": "2",
    "additionRule": "2#109370202"
  },
  {
    "id": 23000007,
    "name": "星系克制对策Ⅴ",
    "desc": "针对星系弱点的进阶对策，能更稳定地扩大克制效果。",
    "funcDesc": "针对【星】系灵感敌人的对策牌，使用后在战斗中能获得额外伤害。",
    "quality": 5,
    "icon": 3000002,
    "type": 3,
    "dropPrice": 2,
    "dropWeight": 100,
    "subType": 0,
    "price": 0,
    "cost": 0,
    "takeOut": 0,
    "disappear": 0,
    "maxStack": 10,
    "directUse": 0,
    "useEffect": "",
    "useDesc": "",
    "bagSkillIds": "",
    "diceList": "",
    "refrain": "2",
    "additionRule": "2#109370208"
  },
  {
    "id": 23000011,
    "name": "兽系克制对策Ⅳ",
    "desc": "针对兽系弱点的基础对策，适合应对兽系灵感敌人。",
    "funcDesc": "针对【兽】系灵感敌人的对策牌，使用后在战斗中能获得额外伤害。",
    "quality": 4,
    "icon": 3000004,
    "type": 3,
    "dropPrice": 1,
    "dropWeight": 100,
    "subType": 0,
    "price": 0,
    "cost": 0,
    "takeOut": 0,
    "disappear": 0,
    "maxStack": 10,
    "directUse": 0,
    "useEffect": "",
    "useDesc": "",
    "bagSkillIds": "",
    "diceList": "",
    "refrain": "4",
    "additionRule": "2#109370203"
  },
  {
    "id": 23000012,
    "name": "兽系克制对策Ⅴ",
    "desc": "针对兽系弱点的进阶对策，能更稳定地扩大克制效果。",
    "funcDesc": "针对【兽】系灵感敌人的对策牌，使用后在战斗中能获得额外伤害。",
    "quality": 5,
    "icon": 3000004,
    "type": 3,
    "dropPrice": 2,
    "dropWeight": 100,
    "subType": 0,
    "price": 0,
    "cost": 0,
    "takeOut": 0,
    "disappear": 0,
    "maxStack": 10,
    "directUse": 0,
    "useEffect": "",
    "useDesc": "",
    "bagSkillIds": "",
    "diceList": "",
    "refrain": "4",
    "additionRule": "2#109370209"
  },
  {
    "id": 23000016,
    "name": "木系克制对策Ⅳ",
    "desc": "针对木系弱点的基础对策，适合应对木系灵感敌人。",
    "funcDesc": "针对【木】系灵感敌人的对策牌，使用后在战斗中能获得额外伤害。",
    "quality": 4,
    "icon": 3000003,
    "type": 3,
    "dropPrice": 1,
    "dropWeight": 100,
    "subType": 0,
    "price": 0,
    "cost": 0,
    "takeOut": 0,
    "disappear": 0,
    "maxStack": 10,
    "directUse": 0,
    "useEffect": "",
    "useDesc": "",
    "bagSkillIds": "",
    "diceList": "",
    "refrain": "3",
    "additionRule": "2#109370204"
  },
  {
    "id": 23000017,
    "name": "木系克制对策Ⅴ",
    "desc": "针对木系弱点的进阶对策，能更稳定地扩大克制效果。",
    "funcDesc": "针对【木】系灵感敌人的对策牌，使用后在战斗中能获得额外伤害。",
    "quality": 5,
    "icon": 3000003,
    "type": 3,
    "dropPrice": 2,
    "dropWeight": 100,
    "subType": 0,
    "price": 0,
    "cost": 0,
    "takeOut": 0,
    "disappear": 0,
    "maxStack": 10,
    "directUse": 0,
    "useEffect": "",
    "useDesc": "",
    "bagSkillIds": "",
    "diceList": "",
    "refrain": "3",
    "additionRule": "2#109370210"
  },
  {
    "id": 23000021,
    "name": "灵系克制对策Ⅳ",
    "desc": "针对灵系弱点的基础对策，适合应对灵系灵感敌人。",
    "funcDesc": "针对【灵】系灵感敌人的对策牌，使用后在战斗中能获得额外伤害。",
    "quality": 4,
    "icon": 3000005,
    "type": 3,
    "dropPrice": 1,
    "dropWeight": 100,
    "subType": 0,
    "price": 0,
    "cost": 0,
    "takeOut": 0,
    "disappear": 0,
    "maxStack": 10,
    "directUse": 0,
    "useEffect": "",
    "useDesc": "",
    "bagSkillIds": "",
    "diceList": "",
    "refrain": "5",
    "additionRule": "2#109370205"
  },
  {
    "id": 23000022,
    "name": "灵系克制对策Ⅴ",
    "desc": "针对灵系弱点的进阶对策，能更稳定地扩大克制效果。",
    "funcDesc": "针对【灵】系灵感敌人的对策牌，使用后在战斗中能获得额外伤害。",
    "quality": 5,
    "icon": 3000005,
    "type": 3,
    "dropPrice": 2,
    "dropWeight": 100,
    "subType": 0,
    "price": 0,
    "cost": 0,
    "takeOut": 0,
    "disappear": 0,
    "maxStack": 10,
    "directUse": 0,
    "useEffect": "",
    "useDesc": "",
    "bagSkillIds": "",
    "diceList": "",
    "refrain": "5",
    "additionRule": "2#109370211"
  },
  {
    "id": 23000026,
    "name": "智系克制对策Ⅳ",
    "desc": "针对智系弱点的基础对策，适合应对智系灵感敌人。",
    "funcDesc": "针对【智】系灵感敌人的对策牌，使用后在战斗中能获得额外伤害。",
    "quality": 4,
    "icon": 3000006,
    "type": 3,
    "dropPrice": 1,
    "dropWeight": 100,
    "subType": 0,
    "price": 0,
    "cost": 0,
    "takeOut": 0,
    "disappear": 0,
    "maxStack": 10,
    "directUse": 0,
    "useEffect": "",
    "useDesc": "",
    "bagSkillIds": "",
    "diceList": "",
    "refrain": "6",
    "additionRule": "2#109370206"
  },
  {
    "id": 23000027,
    "name": "智系克制对策Ⅴ",
    "desc": "针对智系弱点的进阶对策，能更稳定地扩大克制效果。",
    "funcDesc": "针对【智】系灵感敌人的对策牌，使用后在战斗中能获得额外伤害。",
    "quality": 5,
    "icon": 3000006,
    "type": 3,
    "dropPrice": 2,
    "dropWeight": 100,
    "subType": 0,
    "price": 0,
    "cost": 0,
    "takeOut": 0,
    "disappear": 0,
    "maxStack": 10,
    "directUse": 0,
    "useEffect": "",
    "useDesc": "",
    "bagSkillIds": "",
    "diceList": "",
    "refrain": "6",
    "additionRule": "2#109370212"
  },
  {
    "id": 23000033,
    "name": "自然克制对策Ⅴ",
    "desc": "针对自然系弱点的顶级对策，能充分发挥克制效果。",
    "funcDesc": "针对【自然】系灵感敌人的对策牌，使用后在战斗中能获得额外伤害。",
    "quality": 5,
    "icon": 3000008,
    "type": 3,
    "dropPrice": 5,
    "dropWeight": 100,
    "subType": 0,
    "price": 0,
    "cost": 0,
    "takeOut": 0,
    "disappear": 0,
    "maxStack": 10,
    "directUse": 0,
    "useEffect": "",
    "useDesc": "",
    "bagSkillIds": "",
    "diceList": "",
    "refrain": "1#2#3#4",
    "additionRule": ""
  },
  {
    "id": 23000036,
    "name": "原生克制对策Ⅴ",
    "desc": "针对原生系弱点的顶级对策，能充分发挥克制效果。",
    "funcDesc": "针对【原生】系灵感敌人的对策牌，使用后在战斗中能获得额外伤害。",
    "quality": 5,
    "icon": 3000007,
    "type": 3,
    "dropPrice": 5,
    "dropWeight": 100,
    "subType": 0,
    "price": 0,
    "cost": 0,
    "takeOut": 0,
    "disappear": 0,
    "maxStack": 10,
    "directUse": 0,
    "useEffect": "",
    "useDesc": "",
    "bagSkillIds": "",
    "diceList": "",
    "refrain": "5#6",
    "additionRule": ""
  },
  {
    "id": 23000037,
    "name": "全克制对策Ⅵ",
    "desc": "覆盖全部弱点类型的最高阶对策，适合应对任意薄弱灵感敌人。",
    "funcDesc": "针对全系灵感敌人的对策牌，使用后在战斗中能获得额外伤害。",
    "quality": 6,
    "icon": 3000009,
    "type": 3,
    "dropPrice": 6,
    "dropWeight": 100,
    "subType": 0,
    "price": 0,
    "cost": 0,
    "takeOut": 0,
    "disappear": 0,
    "maxStack": 10,
    "directUse": 0,
    "useEffect": "",
    "useDesc": "",
    "bagSkillIds": "",
    "diceList": "",
    "refrain": "1#2#3#4#5#6",
    "additionRule": "2#109370213"
  },
  {
    "id": 24000001,
    "name": "绝望",
    "desc": "像潮湿阴影一样堆积在心口的情绪，越安静，越让人觉得无路可退。",
    "funcDesc": "缺乏耐心的行动会令你获得绝望。达到5张时本次挖掘行动将会失败（可叠加）",
    "quality": 6,
    "icon": 4000022,
    "type": 4,
    "dropPrice": 6,
    "dropWeight": 100,
    "subType": 402,
    "price": 0,
    "cost": 0,
    "takeOut": 0,
    "disappear": 0,
    "maxStack": 5,
    "directUse": 0,
    "useEffect": "",
    "useDesc": "",
    "bagSkillIds": "20001",
    "diceList": "",
    "refrain": "",
    "additionRule": ""
  },
  {
    "id": 24000002,
    "name": "思维混乱",
    "desc": "念头像打散的线团一样缠在一起，想抓住一根，反而会扯乱更多。",
    "funcDesc": "行动后，有概率随机失去一张补给牌（可叠加）",
    "quality": 5,
    "icon": 4000018,
    "type": 4,
    "dropPrice": 6,
    "dropWeight": 100,
    "subType": 402,
    "price": 0,
    "cost": 0,
    "takeOut": 0,
    "disappear": 0,
    "maxStack": 1,
    "directUse": 0,
    "useEffect": "",
    "useDesc": "",
    "bagSkillIds": "20002",
    "diceList": "",
    "refrain": "",
    "additionRule": ""
  },
  {
    "id": 24000003,
    "name": "第三只手",
    "desc": "仿佛凭空多出一只不听使唤的手，越想整理周遭，越容易把一切弄乱。",
    "funcDesc": "行动后，有概率随机失去一张行动牌（可叠加）",
    "quality": 5,
    "icon": 4000012,
    "type": 4,
    "dropPrice": 6,
    "dropWeight": 100,
    "subType": 402,
    "price": 0,
    "cost": 0,
    "takeOut": 0,
    "disappear": 0,
    "maxStack": 1,
    "directUse": 0,
    "useEffect": "",
    "useDesc": "",
    "bagSkillIds": "20003",
    "diceList": "",
    "refrain": "",
    "additionRule": ""
  },
  {
    "id": 24000004,
    "name": "自动应对",
    "desc": "有些动作先于意识发生，像旧习惯在替你生活，而你只能在后面仓促追赶。",
    "funcDesc": "行动后，有概率随机直接使用一张行动牌（可叠加）",
    "quality": 5,
    "icon": 4000006,
    "type": 4,
    "dropPrice": 6,
    "dropWeight": 100,
    "subType": 402,
    "price": 0,
    "cost": 0,
    "takeOut": 0,
    "disappear": 0,
    "maxStack": 1,
    "directUse": 0,
    "useEffect": "",
    "useDesc": "",
    "bagSkillIds": "20004",
    "diceList": "",
    "refrain": "",
    "additionRule": ""
  },
  {
    "id": 24000005,
    "name": "躁郁症",
    "desc": "情绪时而灼热时而低沉，像一根绷到极限又骤然松开的弦。",
    "funcDesc": "通过行动牌回复耐心效果降低（可叠加）",
    "quality": 4,
    "icon": 4000019,
    "type": 4,
    "dropPrice": 6,
    "dropWeight": 100,
    "subType": 402,
    "price": 0,
    "cost": 0,
    "takeOut": 0,
    "disappear": 0,
    "maxStack": 1,
    "directUse": 0,
    "useEffect": "",
    "useDesc": "",
    "bagSkillIds": "20005",
    "diceList": "",
    "refrain": "",
    "additionRule": ""
  },
  {
    "id": 24000006,
    "name": "失明",
    "desc": "视野被一层层抹去，熟悉的轮廓退到远处，只剩下不安还贴在眼前。",
    "funcDesc": "视野强制为1（不可叠加）",
    "quality": 6,
    "icon": 4000007,
    "type": 4,
    "dropPrice": 6,
    "dropWeight": 100,
    "subType": 402,
    "price": 0,
    "cost": 0,
    "takeOut": 0,
    "disappear": 0,
    "maxStack": 1,
    "directUse": 0,
    "useEffect": "",
    "useDesc": "",
    "bagSkillIds": "20006",
    "diceList": "",
    "refrain": "",
    "additionRule": ""
  },
  {
    "id": 24000007,
    "name": "昏昏欲睡",
    "desc": "困意从眼皮和骨缝里慢慢渗出来，把警觉磨成一片迟钝的雾。",
    "funcDesc": "视野范围-1（可叠加）",
    "quality": 4,
    "icon": 4000002,
    "type": 4,
    "dropPrice": 6,
    "dropWeight": 100,
    "subType": 402,
    "price": 0,
    "cost": 0,
    "takeOut": 0,
    "disappear": 0,
    "maxStack": 1,
    "directUse": 0,
    "useEffect": "",
    "useDesc": "",
    "bagSkillIds": "20007",
    "diceList": "",
    "refrain": "",
    "additionRule": ""
  },
  {
    "id": 24000008,
    "name": "厄运缠身",
    "desc": "不顺像无声的影子跟在脚边，越想避开，它越会在关键时刻伸手绊你一下。",
    "funcDesc": "获得物资时，幸运值降低（可叠加）",
    "quality": 4,
    "icon": 4000021,
    "type": 4,
    "dropPrice": 6,
    "dropWeight": 100,
    "subType": 402,
    "price": 0,
    "cost": 0,
    "takeOut": 0,
    "disappear": 0,
    "maxStack": 1,
    "directUse": 0,
    "useEffect": "",
    "useDesc": "",
    "bagSkillIds": "20008",
    "diceList": "",
    "refrain": "",
    "additionRule": ""
  },
  {
    "id": 24000009,
    "name": "树根缠绕",
    "desc": "看不见的根须从地底探上来，缠住脚踝，也缠住每一次想迅速脱身的念头。",
    "funcDesc": "移动消耗的耐心提升（可叠加）",
    "quality": 5,
    "icon": 4000013,
    "type": 4,
    "dropPrice": 6,
    "dropWeight": 100,
    "subType": 402,
    "price": 0,
    "cost": 0,
    "takeOut": 0,
    "disappear": 0,
    "maxStack": 1,
    "directUse": 0,
    "useEffect": "",
    "useDesc": "",
    "bagSkillIds": "20009",
    "diceList": "",
    "refrain": "",
    "additionRule": ""
  },
  {
    "id": 24000010,
    "name": "负重前行",
    "desc": "负担一层层压在身上，不只沉在肩背，也沉进每一个继续前进的决定里。",
    "funcDesc": "移动后，额外消耗耐心（可叠加）",
    "quality": 5,
    "icon": 4000020,
    "type": 4,
    "dropPrice": 6,
    "dropWeight": 100,
    "subType": 402,
    "price": 0,
    "cost": 0,
    "takeOut": 0,
    "disappear": 0,
    "maxStack": 1,
    "directUse": 0,
    "useEffect": "",
    "useDesc": "",
    "bagSkillIds": "20010",
    "diceList": "",
    "refrain": "",
    "additionRule": ""
  },
  {
    "id": 24000011,
    "name": "笨拙",
    "desc": "身体像突然忘记了该如何配合自己，连最熟悉的动作都透着生硬和迟疑。",
    "funcDesc": "检定骰子-1（可叠加）",
    "quality": 4,
    "icon": 4000017,
    "type": 4,
    "dropPrice": 6,
    "dropWeight": 100,
    "subType": 402,
    "price": 0,
    "cost": 0,
    "takeOut": 0,
    "disappear": 0,
    "maxStack": 1,
    "directUse": 0,
    "useEffect": "",
    "useDesc": "",
    "bagSkillIds": "20011",
    "diceList": "",
    "refrain": "",
    "additionRule": ""
  },
  {
    "id": 24000012,
    "name": "理智崩溃",
    "desc": "裂开的不是某个瞬间，而是支撑判断的那条细线，正一点点从脑中抽离。",
    "funcDesc": "撤离时的理智极限降低（可叠加）",
    "quality": 4,
    "icon": 4000016,
    "type": 4,
    "dropPrice": 6,
    "dropWeight": 100,
    "subType": 402,
    "price": 0,
    "cost": 0,
    "takeOut": 0,
    "disappear": 0,
    "maxStack": 1,
    "directUse": 0,
    "useEffect": "",
    "useDesc": "",
    "bagSkillIds": "20012",
    "diceList": "",
    "refrain": "",
    "additionRule": ""
  },
  {
    "id": 24000013,
    "name": "擦枪走火",
    "desc": "紧张、火药与误差在同一刻碰到一起，于是每一次出手都更接近失控。",
    "funcDesc": "战斗后，额外消耗一张对策牌（不可叠加）",
    "quality": 5,
    "icon": 4000008,
    "type": 4,
    "dropPrice": 6,
    "dropWeight": 100,
    "subType": 402,
    "price": 0,
    "cost": 0,
    "takeOut": 0,
    "disappear": 0,
    "maxStack": 1,
    "directUse": 0,
    "useEffect": "",
    "useDesc": "",
    "bagSkillIds": "20013",
    "diceList": "",
    "refrain": "",
    "additionRule": ""
  },
  {
    "id": 24000014,
    "name": "清晨",
    "desc": "清晨把一层苍白薄光铺在地图上，许多东西尚未醒来，却也尚未真正退去。",
    "funcDesc": "可触发【清晨】特定事件。",
    "quality": 1,
    "icon": 4000011,
    "type": 4,
    "dropPrice": 6,
    "dropWeight": 100,
    "subType": 401,
    "price": 0,
    "cost": 0,
    "takeOut": 0,
    "disappear": 1,
    "maxStack": 1,
    "directUse": 0,
    "useEffect": "",
    "useDesc": "",
    "bagSkillIds": "20101",
    "diceList": "",
    "refrain": "",
    "additionRule": ""
  },
  {
    "id": 24000015,
    "name": "中午",
    "desc": "正午的光没有留情，阴影被压到最短，暴露出来的东西也显得更加刺眼。",
    "funcDesc": "可触发【中午】特定事件。\n行动消耗耐心增加。",
    "quality": 1,
    "icon": 4000014,
    "type": 4,
    "dropPrice": 6,
    "dropWeight": 100,
    "subType": 401,
    "price": 0,
    "cost": 0,
    "takeOut": 0,
    "disappear": 1,
    "maxStack": 1,
    "directUse": 0,
    "useEffect": "",
    "useDesc": "",
    "bagSkillIds": "20102",
    "diceList": "",
    "refrain": "",
    "additionRule": ""
  },
  {
    "id": 24000016,
    "name": "夜晚",
    "desc": "夜晚把边界悄悄抹平，远处与近处都更像陷阱，连呼吸声都显得过分清楚。",
    "funcDesc": "可触发【夜晚】特定事件。\n守卫敌人数量增加。",
    "quality": 1,
    "icon": 4000010,
    "type": 4,
    "dropPrice": 6,
    "dropWeight": 100,
    "subType": 401,
    "price": 0,
    "cost": 0,
    "takeOut": 0,
    "disappear": 1,
    "maxStack": 1,
    "directUse": 0,
    "useEffect": "",
    "useDesc": "",
    "bagSkillIds": "20103",
    "diceList": "",
    "refrain": "",
    "additionRule": ""
  },
  {
    "id": 25000001,
    "name": "裹尸布",
    "desc": "噩梦如蝇虫般不绝",
    "funcDesc": "噩梦仍在蠕动，靠近时会泛起与死亡相近的回响。收藏后会获得增益。",
    "quality": 5,
    "icon": 5050003,
    "type": 5,
    "dropPrice": 1,
    "dropWeight": 100,
    "subType": 505,
    "price": 500,
    "cost": 20,
    "takeOut": 1,
    "disappear": 0,
    "maxStack": 1,
    "directUse": 0,
    "useEffect": "",
    "useDesc": "",
    "bagSkillIds": "",
    "diceList": "",
    "refrain": "",
    "additionRule": ""
  },
  {
    "id": 25000002,
    "name": "蜡烛",
    "desc": "冰冷的火焰，小心烫伤",
    "funcDesc": "冷焰亮起时，周围的阴影会短暂退开，露出藏起的痕迹。收藏后会获得增益。进入地图后可以通过供奉获得额外效果。",
    "quality": 6,
    "icon": 5050001,
    "type": 5,
    "dropPrice": 1,
    "dropWeight": 100,
    "subType": 505,
    "price": 1500,
    "cost": 30,
    "takeOut": 1,
    "disappear": 0,
    "maxStack": 1,
    "directUse": 0,
    "useEffect": "",
    "useDesc": "",
    "bagSkillIds": "",
    "diceList": "",
    "refrain": "",
    "additionRule": ""
  },
  {
    "id": 25000003,
    "name": "仪式绳结",
    "desc": "最古老的，最纯粹的信仰",
    "funcDesc": "古老信仰沿着结扣重新收紧，像是在等待某个回应。收藏后会获得增益。进入地图后可以通过供奉获得额外效果。",
    "quality": 6,
    "icon": 5050002,
    "type": 5,
    "dropPrice": 1,
    "dropWeight": 100,
    "subType": 505,
    "price": 1999,
    "cost": 45,
    "takeOut": 1,
    "disappear": 0,
    "maxStack": 1,
    "directUse": 0,
    "useEffect": "",
    "useDesc": "",
    "bagSkillIds": "",
    "diceList": "",
    "refrain": "",
    "additionRule": ""
  },
  {
    "id": 25000004,
    "name": "水晶挂坠",
    "desc": "晶莹如液态",
    "funcDesc": "晶光像液体一样流动，会让附近的回响变得更加清澈。收藏后会获得增益。",
    "quality": 5,
    "icon": 5050004,
    "type": 5,
    "dropPrice": 1,
    "dropWeight": 100,
    "subType": 505,
    "price": 500,
    "cost": 20,
    "takeOut": 1,
    "disappear": 0,
    "maxStack": 1,
    "directUse": 0,
    "useEffect": "",
    "useDesc": "",
    "bagSkillIds": "",
    "diceList": "",
    "refrain": "",
    "additionRule": ""
  },
  {
    "id": 25000005,
    "name": "黑羊角",
    "desc": "母亲最爱的孩子们",
    "funcDesc": "黑羊的气息仍留在角上，母亲的孩子们似乎会因此靠近。收藏后会获得增益。",
    "quality": 4,
    "icon": 5050005,
    "type": 5,
    "dropPrice": 1,
    "dropWeight": 100,
    "subType": 505,
    "price": 300,
    "cost": 20,
    "takeOut": 1,
    "disappear": 0,
    "maxStack": 1,
    "directUse": 0,
    "useEffect": "",
    "useDesc": "",
    "bagSkillIds": "",
    "diceList": "",
    "refrain": "",
    "additionRule": ""
  },
  {
    "id": 25000006,
    "name": "龙舌兰火炬",
    "desc": "“点燃火把，我们下去”",
    "funcDesc": "火光向下探去时，黑暗深处会让出一点前路。收藏后会获得增益。",
    "quality": 5,
    "icon": 5030001,
    "type": 5,
    "dropPrice": 1,
    "dropWeight": 100,
    "subType": 503,
    "price": 500,
    "cost": 20,
    "takeOut": 1,
    "disappear": 0,
    "maxStack": 1,
    "directUse": 0,
    "useEffect": "",
    "useDesc": "",
    "bagSkillIds": "",
    "diceList": "",
    "refrain": "",
    "additionRule": ""
  },
  {
    "id": 25000007,
    "name": "祖母绿项链",
    "desc": "似乎没有什么特别的，不过是文物",
    "funcDesc": "不算奇特，却足够珍贵，能让沉默的旧物重新被注意到。收藏后会获得增益。进入地图后可以通过供奉获得额外效果。",
    "quality": 6,
    "icon": 5030002,
    "type": 5,
    "dropPrice": 1,
    "dropWeight": 100,
    "subType": 503,
    "price": 1999,
    "cost": 50,
    "takeOut": 1,
    "disappear": 0,
    "maxStack": 1,
    "directUse": 0,
    "useEffect": "",
    "useDesc": "",
    "bagSkillIds": "",
    "diceList": "",
    "refrain": "",
    "additionRule": ""
  },
  {
    "id": 25000008,
    "name": "漆黑木枝",
    "desc": "在焦黑中露出新芽",
    "funcDesc": "焦黑枝条里露出的新芽，会带来带有复苏意味的动静。收藏后会获得增益。进入地图后可以通过供奉获得额外效果。",
    "quality": 6,
    "icon": 5030003,
    "type": 5,
    "dropPrice": 1,
    "dropWeight": 100,
    "subType": 503,
    "price": 1600,
    "cost": 50,
    "takeOut": 1,
    "disappear": 0,
    "maxStack": 1,
    "directUse": 0,
    "useEffect": "",
    "useDesc": "",
    "bagSkillIds": "",
    "diceList": "",
    "refrain": "",
    "additionRule": ""
  },
  {
    "id": 25000009,
    "name": "幽光提灯",
    "desc": "魂魄指引道路",
    "funcDesc": "幽光替魂魄照路，也把远处的声音引得更近。收藏后会获得增益。",
    "quality": 5,
    "icon": 5030004,
    "type": 5,
    "dropPrice": 1,
    "dropWeight": 100,
    "subType": 503,
    "price": 500,
    "cost": 20,
    "takeOut": 1,
    "disappear": 0,
    "maxStack": 1,
    "directUse": 0,
    "useEffect": "",
    "useDesc": "",
    "bagSkillIds": "",
    "diceList": "",
    "refrain": "",
    "additionRule": ""
  },
  {
    "id": 25000010,
    "name": "小鬼舌头",
    "desc": "“而且你我都迫切需要”",
    "funcDesc": "这件怪异残物带着迫切的索求，很容易招来回应。收藏后会获得增益。",
    "quality": 4,
    "icon": 5030007,
    "type": 5,
    "dropPrice": 1,
    "dropWeight": 100,
    "subType": 503,
    "price": 300,
    "cost": 20,
    "takeOut": 1,
    "disappear": 0,
    "maxStack": 1,
    "directUse": 0,
    "useEffect": "",
    "useDesc": "",
    "bagSkillIds": "",
    "diceList": "",
    "refrain": "",
    "additionRule": ""
  },
  {
    "id": 25000011,
    "name": "万能钥匙",
    "desc": "连帝国大厦的顶层都能打开",
    "funcDesc": "钥匙能打开的不止是门，也可能是某个被锁住的机会。收藏后会获得增益。",
    "quality": 5,
    "icon": 5040001,
    "type": 5,
    "dropPrice": 1,
    "dropWeight": 100,
    "subType": 504,
    "price": 500,
    "cost": 15,
    "takeOut": 1,
    "disappear": 0,
    "maxStack": 1,
    "directUse": 0,
    "useEffect": "",
    "useDesc": "",
    "bagSkillIds": "",
    "diceList": "",
    "refrain": "",
    "additionRule": ""
  },
  {
    "id": 25000012,
    "name": "红宝石心脏",
    "desc": "跳动的价格",
    "funcDesc": "跳动的心脏本身就是价码，会让周围的注视变得更强烈。收藏后会获得增益。进入地图后可以通过供奉获得额外效果。",
    "quality": 6,
    "icon": 5040002,
    "type": 5,
    "dropPrice": 1,
    "dropWeight": 100,
    "subType": 504,
    "price": 1999,
    "cost": 20,
    "takeOut": 1,
    "disappear": 0,
    "maxStack": 1,
    "directUse": 0,
    "useEffect": "",
    "useDesc": "",
    "bagSkillIds": "",
    "diceList": "",
    "refrain": "",
    "additionRule": ""
  },
  {
    "id": 25000013,
    "name": "黄金猫头鹰",
    "desc": "目光永远盯着你",
    "funcDesc": "猫头鹰的目光不会移开，它会继续替你盯住某个方向。收藏后会获得增益。进入地图后可以通过供奉获得额外效果。",
    "quality": 6,
    "icon": 5040003,
    "type": 5,
    "dropPrice": 1,
    "dropWeight": 100,
    "subType": 504,
    "price": 1600,
    "cost": 50,
    "takeOut": 1,
    "disappear": 0,
    "maxStack": 1,
    "directUse": 0,
    "useEffect": "",
    "useDesc": "",
    "bagSkillIds": "",
    "diceList": "",
    "refrain": "",
    "additionRule": ""
  },
  {
    "id": 25000014,
    "name": "红琥珀",
    "desc": "里面的花纹如毛细血管般延伸",
    "funcDesc": "红琥珀里的脉络逐渐舒展，像有什么正顺着血色浮现。收藏后会获得增益。",
    "quality": 4,
    "icon": 5040008,
    "type": 5,
    "dropPrice": 1,
    "dropWeight": 100,
    "subType": 504,
    "price": 350,
    "cost": 10,
    "takeOut": 1,
    "disappear": 0,
    "maxStack": 1,
    "directUse": 0,
    "useEffect": "",
    "useDesc": "",
    "bagSkillIds": "",
    "diceList": "",
    "refrain": "",
    "additionRule": ""
  },
  {
    "id": 25000015,
    "name": "怀特的胫骨",
    "desc": "从裂痕上看是被勺子一点点敲碎的",
    "funcDesc": "裂痕足以作为证物，沉默中也会留下可以追认的痕迹。收藏后会获得增益。",
    "quality": 4,
    "icon": 5040007,
    "type": 5,
    "dropPrice": 1,
    "dropWeight": 100,
    "subType": 504,
    "price": 300,
    "cost": 20,
    "takeOut": 1,
    "disappear": 0,
    "maxStack": 1,
    "directUse": 0,
    "useEffect": "",
    "useDesc": "",
    "bagSkillIds": "",
    "diceList": "",
    "refrain": "",
    "additionRule": ""
  },
  {
    "id": 25000016,
    "name": "远古乐章",
    "desc": "第一个低音是来自群星的低语",
    "funcDesc": "第一个低音从群星间落下，会唤起远处的低语。收藏后会获得增益。",
    "quality": 5,
    "icon": 5020001,
    "type": 5,
    "dropPrice": 1,
    "dropWeight": 100,
    "subType": 502,
    "price": 500,
    "cost": 20,
    "takeOut": 1,
    "disappear": 0,
    "maxStack": 1,
    "directUse": 0,
    "useEffect": "",
    "useDesc": "",
    "bagSkillIds": "",
    "diceList": "",
    "refrain": "",
    "additionRule": ""
  },
  {
    "id": 25000017,
    "name": "石鬼雕像",
    "desc": "刻画的有些太细致了，像真的看过一样",
    "funcDesc": "石鬼过分细致的凝视，会让附近的回应变得具体起来。收藏后会获得增益。进入地图后可以通过供奉获得额外效果。",
    "quality": 6,
    "icon": 5020002,
    "type": 5,
    "dropPrice": 1,
    "dropWeight": 100,
    "subType": 502,
    "price": 1800,
    "cost": 60,
    "takeOut": 1,
    "disappear": 0,
    "maxStack": 1,
    "directUse": 0,
    "useEffect": "",
    "useDesc": "",
    "bagSkillIds": "",
    "diceList": "",
    "refrain": "",
    "additionRule": ""
  },
  {
    "id": 25000018,
    "name": "灵魂石",
    "desc": "冰冷的如同灵魂",
    "funcDesc": "灵魂石越冷，越容易引来与魂魄有关的动静。收藏后会获得增益。进入地图后可以通过供奉获得额外效果。",
    "quality": 6,
    "icon": 5020003,
    "type": 5,
    "dropPrice": 1,
    "dropWeight": 100,
    "subType": 502,
    "price": 1999,
    "cost": 40,
    "takeOut": 1,
    "disappear": 0,
    "maxStack": 1,
    "directUse": 0,
    "useEffect": "",
    "useDesc": "",
    "bagSkillIds": "",
    "diceList": "",
    "refrain": "",
    "additionRule": ""
  },
  {
    "id": 25000019,
    "name": "黑曜石骰子",
    "desc": "欺诈是一种美德",
    "funcDesc": "骰子落下前无人知道结果，周围也因此多了几分不确定。收藏后会获得增益。",
    "quality": 5,
    "icon": 5020005,
    "type": 5,
    "dropPrice": 1,
    "dropWeight": 100,
    "subType": 502,
    "price": 500,
    "cost": 20,
    "takeOut": 1,
    "disappear": 0,
    "maxStack": 1,
    "directUse": 0,
    "useEffect": "",
    "useDesc": "",
    "bagSkillIds": "",
    "diceList": "",
    "refrain": "",
    "additionRule": ""
  },
  {
    "id": 25000020,
    "name": "纯黑方盒",
    "desc": "黑色的，不可观测的，未知的，恐惧的",
    "funcDesc": "黑盒无法观测，没人能确认它最终会吐出什么。收藏后会获得增益。",
    "quality": 4,
    "icon": 5020008,
    "type": 5,
    "dropPrice": 1,
    "dropWeight": 100,
    "subType": 502,
    "price": 300,
    "cost": 20,
    "takeOut": 1,
    "disappear": 0,
    "maxStack": 1,
    "directUse": 0,
    "useEffect": "",
    "useDesc": "",
    "bagSkillIds": "",
    "diceList": "",
    "refrain": "",
    "additionRule": ""
  },
  {
    "id": 25000021,
    "name": "石制器皿",
    "desc": "经过漫长的岁月依然毫无裂痕",
    "funcDesc": "经得住岁月的器皿，也能稳稳承住一次未知的变化。收藏后会获得增益。",
    "quality": 5,
    "icon": 5010001,
    "type": 5,
    "dropPrice": 1,
    "dropWeight": 100,
    "subType": 501,
    "price": 500,
    "cost": 20,
    "takeOut": 1,
    "disappear": 0,
    "maxStack": 1,
    "directUse": 0,
    "useEffect": "",
    "useDesc": "",
    "bagSkillIds": "",
    "diceList": "",
    "refrain": "",
    "additionRule": ""
  },
  {
    "id": 25000022,
    "name": "黑珍珠项链",
    "desc": "看起来是个贵族的收藏",
    "funcDesc": "贵族旧藏总会被认出，沉在其中的价值感仍未散尽。收藏后会获得增益。",
    "quality": 5,
    "icon": 5010002,
    "type": 5,
    "dropPrice": 1,
    "dropWeight": 100,
    "subType": 501,
    "price": 500,
    "cost": 20,
    "takeOut": 1,
    "disappear": 0,
    "maxStack": 1,
    "directUse": 0,
    "useEffect": "",
    "useDesc": "",
    "bagSkillIds": "",
    "diceList": "",
    "refrain": "",
    "additionRule": ""
  },
  {
    "id": 25000023,
    "name": "羽毛笔",
    "desc": "文字被记录了",
    "funcDesc": "被记录下来的文字仍有分量，会引来与知识有关的回声。收藏后会获得增益。",
    "quality": 5,
    "icon": 5010003,
    "type": 5,
    "dropPrice": 1,
    "dropWeight": 100,
    "subType": 501,
    "price": 500,
    "cost": 20,
    "takeOut": 1,
    "disappear": 0,
    "maxStack": 1,
    "directUse": 0,
    "useEffect": "",
    "useDesc": "",
    "bagSkillIds": "",
    "diceList": "",
    "refrain": "",
    "additionRule": ""
  },
  {
    "id": 25000024,
    "name": "青铜音叉",
    "desc": "叮——",
    "funcDesc": "音叉敲响后，共振会把远处的回应引到近前。收藏后会获得增益。进入地图后可以通过供奉获得额外效果。",
    "quality": 6,
    "icon": 5010004,
    "type": 5,
    "dropPrice": 1,
    "dropWeight": 100,
    "subType": 501,
    "price": 1999,
    "cost": 45,
    "takeOut": 1,
    "disappear": 0,
    "maxStack": 1,
    "directUse": 0,
    "useEffect": "",
    "useDesc": "",
    "bagSkillIds": "",
    "diceList": "",
    "refrain": "",
    "additionRule": ""
  },
  {
    "id": 25000025,
    "name": "奇异壁画",
    "desc": "一场短暂的狩猎",
    "funcDesc": "壁画中的狩猎尚未结束，猎获的气息仍在其中游荡。收藏后会获得增益。进入地图后可以通过供奉获得额外效果。",
    "quality": 6,
    "icon": 5010006,
    "type": 5,
    "dropPrice": 1,
    "dropWeight": 100,
    "subType": 501,
    "price": 1800,
    "cost": 60,
    "takeOut": 1,
    "disappear": 0,
    "maxStack": 1,
    "directUse": 0,
    "useEffect": "",
    "useDesc": "",
    "bagSkillIds": "",
    "diceList": "",
    "refrain": "",
    "additionRule": ""
  },
  {
    "id": 25000026,
    "name": "石制发条",
    "desc": "转动身体，然后继续工作",
    "funcDesc": "发条继续转动，持续运转的象征会带来相应变化。收藏后会获得增益。",
    "quality": 5,
    "icon": 5060001,
    "type": 5,
    "dropPrice": 1,
    "dropWeight": 100,
    "subType": 506,
    "price": 500,
    "cost": 10,
    "takeOut": 1,
    "disappear": 0,
    "maxStack": 1,
    "directUse": 0,
    "useEffect": "",
    "useDesc": "",
    "bagSkillIds": "",
    "diceList": "",
    "refrain": "",
    "additionRule": ""
  },
  {
    "id": 25000027,
    "name": "红泥板",
    "desc": "你们一直对视，直到你彻底闭上了眼",
    "funcDesc": "那道凝视没有结束，闭眼前仍能感到压迫性的回应。收藏后会获得增益。进入地图后可以通过供奉获得额外效果。",
    "quality": 6,
    "icon": 5060007,
    "type": 5,
    "dropPrice": 1,
    "dropWeight": 100,
    "subType": 506,
    "price": 1750,
    "cost": 55,
    "takeOut": 1,
    "disappear": 0,
    "maxStack": 1,
    "directUse": 0,
    "useEffect": "",
    "useDesc": "",
    "bagSkillIds": "",
    "diceList": "",
    "refrain": "",
    "additionRule": ""
  },
  {
    "id": 25000028,
    "name": "水晶头颅",
    "desc": "灵魂在里面发生了折射",
    "funcDesc": "水晶头颅折射魂魄，异样的动静也会随折光浮现。收藏后会获得增益。进入地图后可以通过供奉获得额外效果。",
    "quality": 6,
    "icon": 5060002,
    "type": 5,
    "dropPrice": 1,
    "dropWeight": 100,
    "subType": 506,
    "price": 1999,
    "cost": 50,
    "takeOut": 1,
    "disappear": 0,
    "maxStack": 1,
    "directUse": 0,
    "useEffect": "",
    "useDesc": "",
    "bagSkillIds": "",
    "diceList": "",
    "refrain": "",
    "additionRule": ""
  },
  {
    "id": 25000029,
    "name": "复制石碑",
    "desc": "粘贴过来的",
    "funcDesc": "复制品保留了偏差，异常回应往往就藏在这点偏差里。收藏后会获得增益。",
    "quality": 5,
    "icon": 5060003,
    "type": 5,
    "dropPrice": 1,
    "dropWeight": 100,
    "subType": 506,
    "price": 500,
    "cost": 20,
    "takeOut": 1,
    "disappear": 0,
    "maxStack": 1,
    "directUse": 0,
    "useEffect": "",
    "useDesc": "",
    "bagSkillIds": "",
    "diceList": "",
    "refrain": "",
    "additionRule": ""
  },
  {
    "id": 25000030,
    "name": "铜质硬币",
    "desc": "价值一般，价格不菲",
    "funcDesc": "铜币的价值暧昧，适合用来试探一次不确定的动静。收藏后会获得增益。",
    "quality": 4,
    "icon": 5060004,
    "type": 5,
    "dropPrice": 1,
    "dropWeight": 100,
    "subType": 506,
    "price": 300,
    "cost": 20,
    "takeOut": 1,
    "disappear": 0,
    "maxStack": 1,
    "directUse": 0,
    "useEffect": "",
    "useDesc": "",
    "bagSkillIds": "",
    "diceList": "",
    "refrain": "",
    "additionRule": ""
  }
]