[
  {
    "id": 104001,
    "group": 104001,
    "step": 1,
    "seasons": "",
    "versions": "",
    "maintaskChange": "",
    "desc": "迫近的威胁Ⅰ",
    "desc2": "第4天击败最终入侵怪物<color=#ff0000>【大大大统领！】</color>",
    "progressCondition": "intrudeWin#0",
    "maxProgress": 1,
    "needAccept": 0,
    "prepose": "",
    "failCondition": "intrudeQuit#0",
    "autoDrop": 0,
    "dropShow": ""
  },
  {
    "id": 105001,
    "group": 105001,
    "step": 1,
    "seasons": "",
    "versions": "",
    "maintaskChange": "",
    "desc": "迫近的威胁Ⅰ",
    "desc2": "第5天击败最终入侵怪物<color=#ff0000>【大大大统领！】</color>",
    "progressCondition": "intrudeWin#0",
    "maxProgress": 1,
    "needAccept": 0,
    "prepose": "",
    "failCondition": "intrudeQuit#0",
    "autoDrop": 0,
    "dropShow": ""
  },
  {
    "id": 106001,
    "group": 106001,
    "step": 1,
    "seasons": "",
    "versions": "",
    "maintaskChange": "",
    "desc": "迫近的威胁Ⅰ",
    "desc2": "第4天击败入侵怪物<color=#ff0000>【宇航员幽灵】</color>",
    "progressCondition": "intrudeWin#0",
    "maxProgress": 1,
    "needAccept": 0,
    "prepose": "",
    "failCondition": "intrudeQuit#0",
    "autoDrop": 0,
    "dropShow": ""
  },
  {
    "id": 106002,
    "group": 106001,
    "step": 2,
    "seasons": "",
    "versions": "",
    "maintaskChange": "",
    "desc": "迫近的威胁Ⅱ",
    "desc2": "第6天击败最终入侵怪物<color=#ff0000>【大大大统领！】</color>",
    "progressCondition": "intrudeWin#0",
    "maxProgress": 1,
    "needAccept": 0,
    "prepose": "106001",
    "failCondition": "intrudeQuit#0",
    "autoDrop": 0,
    "dropShow": ""
  },
  {
    "id": 107001,
    "group": 107001,
    "step": 1,
    "seasons": "",
    "versions": "",
    "maintaskChange": "",
    "desc": "迫近的威胁Ⅰ",
    "desc2": "第4天击败入侵怪物<color=#ff0000>【宇航员幽灵】</color>",
    "progressCondition": "intrudeWin#0",
    "maxProgress": 1,
    "needAccept": 0,
    "prepose": "",
    "failCondition": "intrudeQuit#0",
    "autoDrop": 0,
    "dropShow": ""
  },
  {
    "id": 107002,
    "group": 107001,
    "step": 2,
    "seasons": "",
    "versions": "",
    "maintaskChange": "",
    "desc": "迫近的威胁Ⅱ",
    "desc2": "第7天击败最终入侵怪物<color=#ff0000>【？？？】</color>",
    "progressCondition": "intrudeWin#0",
    "maxProgress": 1,
    "needAccept": 0,
    "prepose": "107001",
    "failCondition": "intrudeQuit#0",
    "autoDrop": 0,
    "dropShow": ""
  },
  {
    "id": 108001,
    "group": 108001,
    "step": 1,
    "seasons": "",
    "versions": "",
    "maintaskChange": "",
    "desc": "迫近的威胁Ⅰ",
    "desc2": "第4天击败入侵怪物<color=#ff0000>【宇航员幽灵】</color>",
    "progressCondition": "intrudeWin#0",
    "maxProgress": 1,
    "needAccept": 0,
    "prepose": "",
    "failCondition": "intrudeQuit#0",
    "autoDrop": 0,
    "dropShow": ""
  },
  {
    "id": 108002,
    "group": 108001,
    "step": 2,
    "seasons": "",
    "versions": "",
    "maintaskChange": "",
    "desc": "迫近的威胁Ⅱ",
    "desc2": "第8天击败最终入侵怪物<color=#ff0000>【？？？】</color>",
    "progressCondition": "intrudeWin#0",
    "maxProgress": 1,
    "needAccept": 0,
    "prepose": "108001",
    "failCondition": "intrudeQuit#0",
    "autoDrop": 0,
    "dropShow": ""
  },
  {
    "id": 109001,
    "group": 109001,
    "step": 1,
    "seasons": "",
    "versions": "",
    "maintaskChange": "",
    "desc": "迫近的威胁Ⅰ",
    "desc2": "第4天击败入侵怪物<color=#ff0000>【宇航员幽灵】</color>",
    "progressCondition": "intrudeWin#0",
    "maxProgress": 1,
    "needAccept": 0,
    "prepose": "",
    "failCondition": "intrudeQuit#0",
    "autoDrop": 0,
    "dropShow": ""
  },
  {
    "id": 109002,
    "group": 109001,
    "step": 2,
    "seasons": "",
    "versions": "",
    "maintaskChange": "",
    "desc": "迫近的威胁Ⅱ",
    "desc2": "第9天击败最终入侵怪物<color=#ff0000>【？？？】</color>",
    "progressCondition": "intrudeWin#0",
    "maxProgress": 1,
    "needAccept": 0,
    "prepose": "109001",
    "failCondition": "intrudeQuit#0",
    "autoDrop": 0,
    "dropShow": ""
  },
  {
    "id": 110001,
    "group": 110001,
    "step": 1,
    "seasons": "",
    "versions": "",
    "maintaskChange": "",
    "desc": "迫近的威胁Ⅰ",
    "desc2": "第4天击败入侵怪物<color=#ff0000>【宇航员幽灵】</color>",
    "progressCondition": "intrudeWin#0",
    "maxProgress": 1,
    "needAccept": 0,
    "prepose": "",
    "failCondition": "intrudeQuit#0",
    "autoDrop": 0,
    "dropShow": ""
  },
  {
    "id": 110002,
    "group": 110001,
    "step": 2,
    "seasons": "",
    "versions": "",
    "maintaskChange": "",
    "desc": "迫近的威胁Ⅱ",
    "desc2": "第7天击败入侵怪物<color=#ff0000>【怪异沙漏】</color>",
    "progressCondition": "intrudeWin#0",
    "maxProgress": 1,
    "needAccept": 0,
    "prepose": "110001",
    "failCondition": "intrudeQuit#0",
    "autoDrop": 0,
    "dropShow": ""
  },
  {
    "id": 110003,
    "group": 110001,
    "step": 3,
    "seasons": "",
    "versions": "",
    "maintaskChange": "",
    "desc": "迫近的威胁Ⅲ",
    "desc2": "第10天击败最终入侵怪物<color=#ff0000>【？？？】</color>",
    "progressCondition": "intrudeWin#0",
    "maxProgress": 1,
    "needAccept": 0,
    "prepose": "110002",
    "failCondition": "intrudeQuit#0",
    "autoDrop": 0,
    "dropShow": ""
  },
  {
    "id": 111001,
    "group": 111001,
    "step": 1,
    "seasons": "",
    "versions": "",
    "maintaskChange": "",
    "desc": "迫近的威胁Ⅰ",
    "desc2": "第4天击败入侵怪物<color=#ff0000>【宇航员幽灵】</color>",
    "progressCondition": "intrudeWin#0",
    "maxProgress": 1,
    "needAccept": 0,
    "prepose": "",
    "failCondition": "intrudeQuit#0",
    "autoDrop": 0,
    "dropShow": ""
  },
  {
    "id": 111002,
    "group": 111001,
    "step": 2,
    "seasons": "",
    "versions": "",
    "maintaskChange": "",
    "desc": "迫近的威胁Ⅱ",
    "desc2": "第7天击败入侵怪物<color=#ff0000>【怪异沙漏】</color>",
    "progressCondition": "intrudeWin#0",
    "maxProgress": 1,
    "needAccept": 0,
    "prepose": "111001",
    "failCondition": "intrudeQuit#0",
    "autoDrop": 0,
    "dropShow": ""
  },
  {
    "id": 111003,
    "group": 111001,
    "step": 3,
    "seasons": "",
    "versions": "",
    "maintaskChange": "",
    "desc": "迫近的威胁Ⅲ",
    "desc2": "第11天击败最终入侵怪物<color=#ff0000>【？？？】</color>",
    "progressCondition": "intrudeWin#0",
    "maxProgress": 1,
    "needAccept": 0,
    "prepose": "111002",
    "failCondition": "intrudeQuit#0",
    "autoDrop": 0,
    "dropShow": ""
  },
  {
    "id": 112001,
    "group": 112001,
    "step": 1,
    "seasons": "",
    "versions": "",
    "maintaskChange": "",
    "desc": "迫近的威胁Ⅰ",
    "desc2": "第4天击败入侵怪物<color=#ff0000>【宇航员幽灵】</color>",
    "progressCondition": "intrudeWin#0",
    "maxProgress": 1,
    "needAccept": 0,
    "prepose": "",
    "failCondition": "intrudeQuit#0",
    "autoDrop": 0,
    "dropShow": ""
  },
  {
    "id": 112002,
    "group": 112001,
    "step": 2,
    "seasons": "",
    "versions": "",
    "maintaskChange": "",
    "desc": "迫近的威胁Ⅱ",
    "desc2": "第7天击败入侵怪物<color=#ff0000>【怪异沙漏】</color>",
    "progressCondition": "intrudeWin#0",
    "maxProgress": 1,
    "needAccept": 0,
    "prepose": "112001",
    "failCondition": "intrudeQuit#0",
    "autoDrop": 0,
    "dropShow": ""
  },
  {
    "id": 112003,
    "group": 112001,
    "step": 3,
    "seasons": "",
    "versions": "",
    "maintaskChange": "",
    "desc": "迫近的威胁Ⅲ",
    "desc2": "第12天击败最终入侵怪物<color=#ff0000>【？？？】</color>",
    "progressCondition": "intrudeWin#0",
    "maxProgress": 1,
    "needAccept": 0,
    "prepose": "112002",
    "failCondition": "intrudeQuit#0",
    "autoDrop": 0,
    "dropShow": ""
  }
]